Workbook

Sheet List of Funds
B4: Domestic (U.S.) Stocks (A):
B5: Large-Cap Fund: | C5: Vangaurd Total Stock Market ETF (VTI)
B6: Mid-Cap Fund: | C6: Vangaurd Mid-Cap ETF (VO)
B7: Small-Cap Fund: | C7: Vanguard Small-Cap ETF (VB)
B8: Growth Fund: | C8: Vangaurd US Growth Fund (VWUSX)
B9: Value Fund: | C9: iShares MSCI USA Value factor ETF (VLUE)
B10: Income Fund: | C10: Vanguard High Dividend Yield ETF (VYM)
B11: Consumer Discretionary Fund: | C11: Vanguard Consumer Discretionary ETF (VCR)
B12: Healthcare Fund: | C12: Vanguard Health Care ETF (VHT)
B14: International Stocks (B):
B15: International Developed Fund: | C15: Schwab International Equity ETF(SCHF)
B16: International Developing Fund: | C16: Vanguard FTSE Emerging Markets ETF (VWO)
B17: International Growth Fund: | C17: iShares MSCI EAFE Growth ETF (EFG)
B18: International Value Fund: | C18: iShares MSCI Intl Vakue Factor ETF (IVLU)
B19: International Income Fund: | C19: Vangaurd International High Dividend Yield ETF (VYMI)
B21: Bonds (C):
B22: Domestic Investment Grade: | C22: Fidelity Investment Grade Bond Fund (FBNDX)
B23: Domestic Speculative Grade: | C23: Vangaurd High-Yield Corporate Fund Investor Shares (VWEHX)
B24: International Investment Grade: | C24: Invesco International Corporate Bond ETF (PICB)
B25: International Speculative Grade: | C25: iShares International High Yield Bond ETF (HYXU)
B27: Commodities (D):
B28: Basket of 3 Oil/Gas Stocks | C28: ExxonMobil (XOM), Chevron (CVX), ConocoPhillips (COP)
B29: Basket of 3 Timber Stocks | C29: West Fraser Timber Company (WFG), Boise Cascade (BCC), Enviva Partners, LP (EVA)
B30: Domestic REIT: | C30: Store Capital Corporation (STOR)

Sheet Return Data
B1: VTI | C1: VO | D1: VB | E1: VWUSX | F1: VLUE | G1: VYM | H1: VCR | I1: VHT | J1: SCHF | K1: VWO | L1: EFG | M1: IVLU | N1: VYMI | O1: FBNDX | P1: VWEHX | Q1: PICB | R1: HYXU | S1: Oil Basket | T1: Timber Basket | U1: STOR | W1: GSPC
B2: 0.020135642 | C2: 0.023392872 | D2: 0.021898284 | E2: 0.02666322 | F2: -0.0059279467 | G2: 0.035551053 | H2: 0.023273062 | I2: 0.065273197 | J2: 0.0052099208 | K2: 0.048335784 | L2: 0.0074349554 | M2: -0.0033727917 | N2: 0.0088539492 | O2: 0.0052842108 | P2: -0.0070507259 | Q2: -0.012940664 | R2: -0.017561315 | S2: 0.010113431 | T2: -0.017080732 | U2: 0.032035467 | W2: 0.017859382
B3: -0.091761055 | C3: -0.098025633 | D3: -0.11112112 | E3: -0.09085557 | F3: -0.11052319 | G3: -0.086647546 | H3: -0.088754558 | I3: -0.091387839 | J3: -0.054022923 | K3: -0.033449906 | L3: -0.050489939 | M3: -0.062857088 | N3: -0.041566704 | O3: 0.015302994 | P3: -0.021294341 | Q3: 0.013770781 | R3: 0.0092931443 | S3: -0.095157768 | T3: -0.082211878 | U3: -0.044112867 | W3: -0.091776956
B4: 0.085402381 | C4: 0.10471827 | D4: 0.11712965 | E4: 0.094755476 | F4: 0.098387498 | G4: 0.061033574 | H4: 0.10085122 | I4: 0.059340365 | J4: 0.07195753 | K4: 0.096587827 | L4: 0.061676722 | M4: 0.080475472 | N4: 0.070375171 | O4: 0.015530912 | P4: 0.049409077 | Q4: 0.02918282 | R4: 0.023395434 | S4: 0.071385125 | T4: 0.14658667 | U4: 0.14164603 | W4: 0.078684405
B5: 0.035587945 | C5: 0.042581103 | D5: 0.048559231 | E5: 0.044093868 | F5: 0.01894367 | G5: 0.037703857 | H5: 0.015026781 | I5: 0.016398978 | J5: 0.024021045 | K5: -0.0038296917 | L5: 0.033410483 | M5: 0.0059243427 | N5: 0.015606851 | O5: 0.0010351346 | P5: 0.01501068 | Q5: 0.006008248 | R5: 0.012340873 | S5: 0.05027969 | T5: -0.041103701 | U5: 0.0046414171 | W5: 0.02972893
B6: 0.014167673 | C6: 0.013529287 | D6: -0.0085803286 | E6: 0.016683683 | F6: -0.0095208703 | G6: 0.0052353703 | H6: 0.027674923 | I6: 0.0038264212 | J6: 0.0061055866 | K6: 0.023148306 | L6: 0.022037338 | M6: -0.00075698964 | N6: 0.0021617997 | O6: 0.019336132 | P6: 0.0099693849 | Q6: 0.0078449642 | R6: -0.0039967891 | S6: 0.012047566 | T6: 0.0016050625 | U6: 0.041976313 | W6: 0.017924288
B7: 0.03925079 | C7: 0.037137855 | D7: 0.035863903 | E7: 0.14328428 | F7: 0.034184583 | G7: 0.028367844 | H7: 0.051041047 | I7: -0.026959034 | J7: 0.028744583 | K7: 0.021411964 | L7: 0.034990614 | M7: 0.01717745 | N7: 0.02842596 | O7: 0.0024170414 | P7: 0.014951046 | Q7: -0.00022520302 | R7: 0.012038483 | S7: -0.028668156 | T7: 0.039923455 | U7: -0.0053730284 | W7: 0.039313435
B8: -0.064498857 | C8: -0.060580456 | D8: -0.071771422 | E8: -0.060694927 | F8: -0.096016368 | G8: -0.063117328 | H8: -0.078969371 | I8: -0.026753652 | J8: -0.052157622 | K8: -0.063810271 | L8: -0.042040943 | M8: -0.073675848 | N8: -0.053363198 | O8: 0.015097145 | P8: -0.010827392 | Q8: -0.010945912 | R8: -0.019230848 | S8: -0.070668176 | T8: -0.1596295 | U8: 0.027010607 | W8: -0.065777726
B9: 0.070780583 | C9: 0.071010117 | D9: 0.069689174 | E9: 0.073475491 | F9: 0.095697945 | G9: 0.066443621 | H9: 0.077568828 | I9: 0.071989839 | J9: 0.059591161 | K9: 0.053718492 | L9: 0.064857947 | M9: 0.052624997 | N9: 0.053720491 | O9: 0.014776506 | P9: 0.027245509 | Q9: 0.033051183 | R9: 0.039417804 | S9: 0.070140348 | T9: 0.1520627 | U9: -0.020317144 | W9: 0.068930183
B10: 0.01412512 | C10: 0.013101356 | D10: 0.012000213 | E10: 0.012621592 | F10: 0.016011972 | G10: 0.0072099112 | H10: 0.011595048 | I10: -0.01305031 | J10: -0.019632322 | K10: -0.018104649 | L10: -0.011390358 | M10: -0.020824068 | N10: -0.02688181 | O10: 0.0023571247 | P10: 0.0044564918 | Q10: -0.013418341 | R10: -0.019642119 | S10: -0.022288071 | T10: -0.072549338 | U10: 0.030732144 | W10: 0.013128195
B11: -0.02082677 | C11: -0.027576177 | D11: -0.039674585 | E11: -0.01677858 | F11: -0.045217683 | G11: -0.021020431 | H11: -0.017358461 | I11: -0.011767143 | J11: -0.018753707 | K11: -0.03256711 | L11: -0.0055103326 | M11: -0.035445042 | N11: -0.034488336 | O11: 0.023245905 | P11: 0.0095835561 | Q11: 0.0088005908 | R11: 0.00039678611 | S11: -0.07278911 | T11: 0.045102442 | U11: 0.10377091 | W11: -0.018091653
B12: 0.017792804 | C12: 0.020970813 | D12: 0.013667671 | E12: -0.012189369 | F12: 0.048549396 | G12: 0.038954588 | H12: 0.013397385 | I12: -0.0079013048 | J12: 0.032069733 | K12: 0.0091090802 | L12: 0.013852226 | M12: 0.046853177 | N12: 0.041206644 | O12: -0.0038665768 | P12: 0.0042625336 | Q12: -0.0079514433 | R12: -0.0093199609 | S12: 0.043523102 | T12: 0.062331578 | U12: -6.1660721e-05 | W12: 0.017181168
B13: 0.021060071 | C13: 0.011098215 | D13: 0.016504843 | E13: 0.025419733 | F13: 0.028400774 | G13: 0.010481276 | H13: 0.0071065245 | I13: 0.047829499 | J13: 0.031387585 | K13: 0.039493334 | L13: 0.032666691 | M13: 0.039052051 | N13: 0.033002221 | O13: 0.0045210737 | P13: 0.0061315844 | Q13: 0.025883421 | R13: 0.023418804 | S13: -0.029235912 | T13: 0.10053296 | U13: 0.082598301 | W13: 0.020431747
... B37: 0.066873818 | C37: 0.065889508 | D37: 0.049480953 | E37: 0.072737368 | F37: 0.024826216 | G37: 0.049250121 | H37: 0.093041262 | I37: 0.045678912 | J37: 0.03255814 | K37: 0.012997401 | L37: 0.042077581 | M37: 0.012057565 | N37: 0.029674489 | O37: -0.0011904762 | P37: -0.0066889632 | Q37: 0.0060383631 | R37: -0.0050881337 | S37: 0.11011797 | T37: 0.079032944 | U37: 0.07180768 | W37: 0.069143873
A38: Beta Coefficient | B38: =SLOPE(B2:B37,W2:W37) -> 1.0290576 | C38: =SLOPE(C$2:C$37,$W$2:$W$37) -> 1.1063456 | D38: =SLOPE(D$2:D$37,$W$2:$W$37) -> 1.1927321 | E38: =SLOPE(E$2:E$37,$W$2:$W$37) -> 1.1027866 | F38: =SLOPE(F$2:F$37,$W$2:$W$37) -> 1.1038458 | G38: =SLOPE(G$2:G$37,$W$2:$W$37) -> 0.91877651 | H38: =SLOPE(H$2:H$37,$W$2:$W$37) -> 1.2682613 | I38: =SLOPE(I$2:I$37,$W$2:$W$37) -> 0.73932412 | J38: =SLOPE(J$2:J$37,$W$2:$W$37) -> 0.84071189 | ... U38: =SLOPE(U$2:U$37,$W$2:$W$37) -> 1.4737245
A39: Expected Return | B39: =0.02+B38*(0.075-0.02) -> 0.07659817 | C39: =0.02+C38*(0.075-0.02) -> 0.08084901 | D39: =0.02+D38*(0.075-0.02) -> 0.085600267 | E39: =0.02+E38*(0.075-0.02) -> 0.080653261 | F39: =0.02+F38*(0.075-0.02) -> 0.08071152 | G39: =0.02+G38*(0.075-0.02) -> 0.070532708 | H39: =0.02+H38*(0.075-0.02) -> 0.089754373 | I39: =0.02+I38*(0.075-0.02) -> 0.060662826 | ... U39: =0.02+U38*(0.075-0.02) -> 0.10105485
A41: Group A | B41: VTI | C41: Adj Close | D41: Return | E41: VO | F41: Adj Close | G41: Return | H41: VB | I41: Adj Close | J41: Return | K41: VWUSX | L41: Adj Close | M41: Return | N41: VLUE | O41: Adj Close | P41: Return | Q41: VYM | R41: Adj Close | S41: Return | T41: VCR | U41: Adj Close | V41: Return | W41: VHT | X41: Adj Close | Y41: Return | Z41: Group B | AA41: SCHF | AB41: Adj Close | AC41: Return | AD41: VWO | AE41: Adj Close | AF41: Return | AG41: EFG | AH41: Adj Close | AI41: Return | AJ41: IVLU | AK41: Adj Close | AL41: Return | AM41: VYMI | AN41: Adj Close | AO41: Return
B42: 43404 | C42: 131.523 | E42: 43404 | F42: 143.5993 | H42: 43404 | I42: 140.116 | K42: 43404 | L42: 30.44231 | N42: 43404 | O42: 76.19333 | Q42: 43404 | R42: 75.49453 | T42: 43404 | U42: 155.0548 | W42: 43404 | X42: 158.86 | AA42: 43404 | AB42: 28.05225 | AD42: 43404 | AE42: 35.00326 | AG42: 43404 | AH42: 69.64803 | AJ42: 43404 | AK42: 21.83651 | AM42: 43404 | AN42: 52.14961
B43: 43434 | C43: 134.1713 | D43: =(C43-C42)/C42 -> 0.020135642 | E43: 43434 | F43: 146.9585 | G43: =(F43-F42)/F42 -> 0.023392872 | H43: 43434 | I43: 143.1843 | J43: =(I43-I42)/I42 -> 0.021898284 | K43: 43434 | L43: 31.254 | M43: =(L43-L42)/L42 -> 0.02666322 | N43: 43434 | O43: 75.74166 | P43: =(O43-O42)/O42 -> -0.0059279467 | Q43: 43434 | R43: 78.17844 | S43: =(R43-R42)/R42 -> 0.035551053 | T43: 43434 | U43: 158.6634 | V43: =(U43-U42)/U42 -> 0.023273062 | W43: 43434 | X43: 169.2293 | Y43: =(X43-X42)/X42 -> 0.065273197 | AA43: 43434 | AB43: 28.1984 | AC43: =(AB43-AB42)/AB42 -> 0.0052099208 | AD43: 43434 | AE43: 36.69517 | AF43: =(AE43-AE42)/AE42 -> 0.048335784 | AG43: 43434 | AH43: 70.16586 | AI43: =(AH43-AH42)/AH42 -> 0.0074349554 | AJ43: 43434 | AK43: 21.76286 | AL43: =(AK43-AK42)/AK42 -> -0.0033727917 | AM43: 43434 | AN43: 52.61134 | AO43: =(AN43-AN42)/AN42 -> 0.0088539492
B44: 43465 | C44: 121.8596 | D44: =(C44-C43)/C43 -> -0.091761055 | E44: 43465 | F44: 132.5528 | G44: =(F44-F43)/F43 -> -0.098025633 | H44: 43465 | I44: 127.2735 | J44: =(I44-I43)/I43 -> -0.11112112 | K44: 43465 | L44: 28.4144 | M44: =(L44-L43)/L43 -> -0.09085557 | N44: 43465 | O44: 67.37045 | P44: =(O44-O43)/O43 -> -0.11052319 | Q44: 43465 | R44: 71.40447 | S44: =(R44-R43)/R43 -> -0.086647546 | T44: 43465 | U44: 144.5813 | V44: =(U44-U43)/U43 -> -0.088754558 | W44: 43465 | X44: 153.7638 | Y44: =(X44-X43)/X43 -> -0.091387839 | AA44: 43465 | AB44: 26.67504 | AC44: =(AB44-AB43)/AB43 -> -0.054022923 | AD44: 43465 | AE44: 35.46772 | AF44: =(AE44-AE43)/AE43 -> -0.033449906 | AG44: 43465 | AH44: 66.62319 | AI44: =(AH44-AH43)/AH43 -> -0.050489939 | AJ44: 43465 | AK44: 20.39491 | AL44: =(AK44-AK43)/AK43 -> -0.062857088 | AM44: 43465 | AN44: 50.42446 | AO44: =(AN44-AN43)/AN43 -> -0.041566704
B45: 43496 | C45: 132.2667 | D45: =(C45-C44)/C44 -> 0.085402381 | E45: 43496 | F45: 146.4335 | G45: =(F45-F44)/F44 -> 0.10471827 | H45: 43496 | I45: 142.181 | J45: =(I45-I44)/I44 -> 0.11712965 | K45: 43496 | L45: 31.10682 | M45: =(L45-L44)/L44 -> 0.094755476 | N45: 43496 | O45: 73.99886 | P45: =(O45-O44)/O44 -> 0.098387498 | Q45: 43496 | R45: 75.76254 | S45: =(R45-R44)/R44 -> 0.061033574 | T45: 43496 | U45: 159.1625 | V45: =(U45-U44)/U44 -> 0.10085122 | W45: 43496 | X45: 162.8882 | Y45: =(X45-X44)/X44 -> 0.059340365 | AA45: 43496 | AB45: 28.59451 | AC45: =(AB45-AB44)/AB44 -> 0.07195753 | AD45: 43496 | AE45: 38.89347 | AF45: =(AE45-AE44)/AE44 -> 0.096587827 | AG45: 43496 | AH45: 70.73229 | AI45: =(AH45-AH44)/AH44 -> 0.061676722 | AJ45: 43496 | AK45: 22.0362 | AL45: =(AK45-AK44)/AK44 -> 0.080475472 | AM45: 43496 | AN45: 53.97309 | AO45: =(AN45-AN44)/AN44 -> 0.070375171
B46: 43524 | C46: 136.9738 | D46: =(C46-C45)/C45 -> 0.035587945 | E46: 43524 | F46: 152.6688 | G46: =(F46-F45)/F45 -> 0.042581103 | H46: 43524 | I46: 149.0852 | J46: =(I46-I45)/I45 -> 0.048559231 | K46: 43524 | L46: 32.47844 | M46: =(L46-L45)/L45 -> 0.044093868 | N46: 43524 | O46: 75.40067 | P46: =(O46-O45)/O45 -> 0.01894367 | Q46: 43524 | R46: 78.61908 | S46: =(R46-R45)/R45 -> 0.037703857 | T46: 43524 | U46: 161.5542 | V46: =(U46-U45)/U45 -> 0.015026781 | W46: 43524 | X46: 165.5594 | Y46: =(X46-X45)/X45 -> 0.016398978 | AA46: 43524 | AB46: 29.28138 | AC46: =(AB46-AB45)/AB45 -> 0.024021045 | AD46: 43524 | AE46: 38.74452 | AF46: =(AE46-AE45)/AE45 -> -0.0038296917 | AG46: 43524 | AH46: 73.09549 | AI46: =(AH46-AH45)/AH45 -> 0.033410483 | AJ46: 43524 | AK46: 22.16675 | AL46: =(AK46-AK45)/AK45 -> 0.0059243427 | AM46: 43524 | AN46: 54.81544 | AO46: =(AN46-AN45)/AN45 -> 0.015606851
B47: 43553 | C47: 138.9144 | D47: =(C47-C46)/C46 -> 0.014167673 | E47: 43553 | F47: 154.7343 | G47: =(F47-F46)/F46 -> 0.013529287 | H47: 43553 | I47: 147.806 | J47: =(I47-I46)/I46 -> -0.0085803286 | K47: 43553 | L47: 33.0203 | M47: =(L47-L46)/L46 -> 0.016683683 | N47: 43553 | O47: 74.68279 | P47: =(O47-O46)/O46 -> -0.0095208703 | Q47: 43553 | R47: 79.03068 | S47: =(R47-R46)/R46 -> 0.0052353703 | T47: 43553 | U47: 166.0252 | V47: =(U47-U46)/U46 -> 0.027674923 | W47: 43553 | X47: 166.1929 | Y47: =(X47-X46)/X46 -> 0.0038264212 | AA47: 43553 | AB47: 29.46016 | AC47: =(AB47-AB46)/AB46 -> 0.0061055866 | AD47: 43553 | AE47: 39.64139 | AF47: =(AE47-AE46)/AE46 -> 0.023148306 | AG47: 43553 | AH47: 74.70632 | AI47: =(AH47-AH46)/AH46 -> 0.022037338 | AJ47: 43553 | AK47: 22.14997 | AL47: =(AK47-AK46)/AK46 -> -0.00075698964 | AM47: 43553 | AN47: 54.93394 | AO47: =(AN47-AN46)/AN46 -> 0.0021617997
B48: 43585 | C48: 144.3669 | D48: =(C48-C47)/C47 -> 0.03925079 | E48: 43585 | F48: 160.4808 | G48: =(F48-F47)/F47 -> 0.037137855 | H48: 43585 | I48: 153.1069 | J48: =(I48-I47)/I47 -> 0.035863903 | K48: 43585 | L48: 37.75159 | M48: =(L48-L47)/L47 -> 0.14328428 | N48: 43585 | O48: 77.23579 | P48: =(O48-O47)/O47 -> 0.034184583 | Q48: 43585 | R48: 81.27261 | S48: =(R48-R47)/R47 -> 0.028367844 | T48: 43585 | U48: 174.4993 | V48: =(U48-U47)/U47 -> 0.051041047 | W48: 43585 | X48: 161.7125 | Y48: =(X48-X47)/X47 -> -0.026959034 | AA48: 43585 | AB48: 30.30698 | AC48: =(AB48-AB47)/AB47 -> 0.028744583 | AD48: 43585 | AE48: 40.49019 | AF48: =(AE48-AE47)/AE47 -> 0.021411964 | AG48: 43585 | AH48: 77.32034 | AI48: =(AH48-AH47)/AH47 -> 0.034990614 | AJ48: 43585 | AK48: 22.53045 | AL48: =(AK48-AK47)/AK47 -> 0.01717745 | AM48: 43585 | AN48: 56.49549 | AO48: =(AN48-AN47)/AN47 -> 0.02842596
B49: 43616 | C49: 135.0554 | D49: =(C49-C48)/C48 -> -0.064498857 | E49: 43616 | F49: 150.7588 | G49: =(F49-F48)/F48 -> -0.060580456 | H49: 43616 | I49: 142.1182 | J49: =(I49-I48)/I48 -> -0.071771422 | K49: 43616 | L49: 35.46026 | M49: =(L49-L48)/L48 -> -0.060694927 | N49: 43616 | O49: 69.81989 | P49: =(O49-O48)/O48 -> -0.096016368 | Q49: 43616 | R49: 76.1429 | S49: =(R49-R48)/R48 -> -0.063117328 | T49: 43616 | U49: 160.7192 | V49: =(U49-U48)/U48 -> -0.078969371 | W49: 43616 | X49: 157.3861 | Y49: =(X49-X48)/X48 -> -0.026753652 | AA49: 43616 | AB49: 28.72624 | AC49: =(AB49-AB48)/AB48 -> -0.052157622 | AD49: 43616 | AE49: 37.9065 | AF49: =(AE49-AE48)/AE48 -> -0.063810271 | AG49: 43616 | AH49: 74.06972 | AI49: =(AH49-AH48)/AH48 -> -0.042040943 | AJ49: 43616 | AK49: 20.8705 | AL49: =(AK49-AK48)/AK48 -> -0.073675848 | AM49: 43616 | AN49: 53.48071 | AO49: =(AN49-AN48)/AN48 -> -0.053363198
B50: 43644 | C50: 144.6147 | D50: =(C50-C49)/C49 -> 0.070780583 | E50: 43644 | F50: 161.4642 | G50: =(F50-F49)/F49 -> 0.071010117 | H50: 43644 | I50: 152.0223 | J50: =(I50-I49)/I49 -> 0.069689174 | K50: 43644 | L50: 38.06572 | M50: =(L50-L49)/L49 -> 0.073475491 | N50: 43644 | O50: 76.50151 | P50: =(O50-O49)/O49 -> 0.095697945 | Q50: 43644 | R50: 81.20211 | S50: =(R50-R49)/R49 -> 0.066443621 | T50: 43644 | U50: 173.186 | V50: =(U50-U49)/U49 -> 0.077568828 | W50: 43644 | X50: 168.7163 | Y50: =(X50-X49)/X49 -> 0.071989839 | AA50: 43644 | AB50: 30.43807 | AC50: =(AB50-AB49)/AB49 -> 0.059591161 | AD50: 43644 | AE50: 39.94278 | AF50: =(AE50-AE49)/AE49 -> 0.053718492 | AG50: 43644 | AH50: 78.87373 | AI50: =(AH50-AH49)/AH49 -> 0.064857947 | AJ50: 43644 | AK50: 21.96881 | AL50: =(AK50-AK49)/AK49 -> 0.052624997 | AM50: 43644 | AN50: 56.35372 | AO50: =(AN50-AN49)/AN49 -> 0.053720491
B51: 43677 | C51: 146.6574 | D51: =(C51-C50)/C50 -> 0.01412512 | E51: 43677 | F51: 163.5796 | G51: =(F51-F50)/F50 -> 0.013101356 | H51: 43677 | I51: 153.8466 | J51: =(I51-I50)/I50 -> 0.012000213 | K51: 43677 | L51: 38.54617 | M51: =(L51-L50)/L50 -> 0.012621592 | N51: 43677 | O51: 77.72645 | P51: =(O51-O50)/O50 -> 0.016011972 | Q51: 43677 | R51: 81.78757 | S51: =(R51-R50)/R50 -> 0.0072099112 | T51: 43677 | U51: 175.1941 | V51: =(U51-U50)/U50 -> 0.011595048 | W51: 43677 | X51: 166.5145 | Y51: =(X51-X50)/X50 -> -0.01305031 | AA51: 43677 | AB51: 29.8405 | AC51: =(AB51-AB50)/AB50 -> -0.019632322 | AD51: 43677 | AE51: 39.21963 | AF51: =(AE51-AE50)/AE50 -> -0.018104649 | AG51: 43677 | AH51: 77.97533 | AI51: =(AH51-AH50)/AH50 -> -0.011390358 | AJ51: 43677 | AK51: 21.51133 | AL51: =(AK51-AK50)/AK50 -> -0.020824068 | AM51: 43677 | AN51: 54.83883 | AO51: =(AN51-AN50)/AN50 -> -0.02688181
B52: 43707 | C52: 143.603 | D52: =(C52-C51)/C51 -> -0.02082677 | E52: 43707 | F52: 159.0687 | G52: =(F52-F51)/F51 -> -0.027576177 | H52: 43707 | I52: 147.7428 | J52: =(I52-I51)/I51 -> -0.039674585 | K52: 43707 | L52: 37.89942 | M52: =(L52-L51)/L51 -> -0.01677858 | N52: 43707 | O52: 74.21184 | P52: =(O52-O51)/O51 -> -0.045217683 | Q52: 43707 | R52: 80.06836 | S52: =(R52-R51)/R51 -> -0.021020431 | T52: 43707 | U52: 172.153 | V52: =(U52-U51)/U51 -> -0.017358461 | W52: 43707 | X52: 164.5551 | Y52: =(X52-X51)/X51 -> -0.011767143 | AA52: 43707 | AB52: 29.28088 | AC52: =(AB52-AB51)/AB51 -> -0.018753707 | AD52: 43707 | AE52: 37.94236 | AF52: =(AE52-AE51)/AE51 -> -0.03256711 | AG52: 43707 | AH52: 77.54566 | AI52: =(AH52-AH51)/AH51 -> -0.0055103326 | AJ52: 43707 | AK52: 20.74886 | AL52: =(AK52-AK51)/AK51 -> -0.035445042 | AM52: 43707 | AN52: 52.94753 | AO52: =(AN52-AN51)/AN51 -> -0.034488336
B53: 43738 | C53: 146.1581 | D53: =(C53-C52)/C52 -> 0.017792804 | E53: 43738 | F53: 162.4045 | G53: =(F53-F52)/F52 -> 0.020970813 | H53: 43738 | I53: 149.7621 | J53: =(I53-I52)/I52 -> 0.013667671 | K53: 43738 | L53: 37.43745 | M53: =(L53-L52)/L52 -> -0.012189369 | N53: 43738 | O53: 77.81478 | P53: =(O53-O52)/O52 -> 0.048549396 | Q53: 43738 | R53: 83.18739 | S53: =(R53-R52)/R52 -> 0.038954588 | T53: 43738 | U53: 174.4594 | V53: =(U53-U52)/U52 -> 0.013397385 | W53: 43738 | X53: 163.2549 | Y53: =(X53-X52)/X52 -> -0.0079013048 | AA53: 43738 | AB53: 30.21991 | AC53: =(AB53-AB52)/AB52 -> 0.032069733 | AD53: 43738 | AE53: 38.28798 | AF53: =(AE53-AE52)/AE52 -> 0.0091090802 | AG53: 43738 | AH53: 78.61984 | AI53: =(AH53-AH52)/AH52 -> 0.013852226 | AJ53: 43738 | AK53: 21.72101 | AL53: =(AK53-AK52)/AK52 -> 0.046853177 | AM53: 43738 | AN53: 55.12932 | AO53: =(AN53-AN52)/AN52 -> 0.041206644
B54: 43769 | C54: 149.2362 | D54: =(C54-C53)/C53 -> 0.021060071 | E54: 43769 | F54: 164.2069 | G54: =(F54-F53)/F53 -> 0.011098215 | H54: 43769 | I54: 152.2339 | J54: =(I54-I53)/I53 -> 0.016504843 | K54: 43769 | L54: 38.3891 | M54: =(L54-L53)/L53 -> 0.025419733 | N54: 43769 | O54: 80.02478 | P54: =(O54-O53)/O53 -> 0.028400774 | Q54: 43769 | R54: 84.0593 | S54: =(R54-R53)/R53 -> 0.010481276 | T54: 43769 | U54: 175.6992 | V54: =(U54-U53)/U53 -> 0.0071065245 | W54: 43769 | X54: 171.0633 | Y54: =(X54-X53)/X53 -> 0.047829499 | AA54: 43769 | AB54: 31.16844 | AC54: =(AB54-AB53)/AB53 -> 0.031387585 | AD54: 43769 | AE54: 39.8001 | AF54: =(AE54-AE53)/AE53 -> 0.039493334 | AG54: 43769 | AH54: 81.18809 | AI54: =(AH54-AH53)/AH53 -> 0.032666691 | AJ54: 43769 | AK54: 22.56926 | AL54: =(AK54-AK53)/AK53 -> 0.039052051 | AM54: 43769 | AN54: 56.94871 | AO54: =(AN54-AN53)/AN53 -> 0.033002221
... B78: 44498 | C78: 236.91 | D78: =(C78-C77)/C77 -> 0.066873818 | E78: 44498 | F78: 252.36 | G78: =(F78-F77)/F77 -> 0.065889508 | H78: 44498 | I78: 229.49 | J78: =(I78-I77)/I77 -> 0.049480953 | K78: 44498 | L78: 77.28 | M78: =(L78-L77)/L77 -> 0.072737368 | N78: 44498 | O78: 103.2 | P78: =(O78-O77)/O77 -> 0.024826216 | Q78: 44498 | R78: 108.44 | S78: =(R78-R77)/R77 -> 0.049250121 | T78: 44498 | U78: 338.81 | V78: =(U78-U77)/U77 -> 0.093041262 | W78: 44498 | X78: 258.45 | Y78: =(X78-X77)/X77 -> 0.045678912 | AA78: 44498 | AB78: 39.96 | AC78: =(AB78-AB77)/AB77 -> 0.03255814 | AD78: 44498 | AE78: 50.66 | AF78: =(AE78-AE77)/AE77 -> 0.012997401 | AG78: 44498 | AH78: 110.95 | AI78: =(AH78-AH77)/AH77 -> 0.042077581 | AJ78: 44498 | AK78: 26.02 | AL78: =(AK78-AK77)/AK77 -> 0.012057565 | AM78: 44498 | AN78: 68.01 | AO78: =(AN78-AN77)/AN77 -> 0.029674489
A81: Group C | B81: FBNDX | C81: Adj Close | E81: VWEHX | F81: Adj Close | G81: Return | H81: PICB | I81: Adj Close | J81: Return | K81: HYXU | L81: Adj Close | M81: Return | N81: Group D | O81: OIL BASKET> | P81: Average Return | Q81: XOM | R81: Adj Close | S81: Return | T81: CVX | U81: Adj Close | V81: Return | W81: COP | X81: Adj Close | Y81: Return | Z81: Timber Basket> | AA81: Average Return | AB81: WFG | AC81: Adj Close | AD81: Return | AE81: BCC | AF81: Adj Close | AG81: Return | AH81: EVA | AI81: Adj Close | AK81: REIT> | AL81: STOR | AM81: Adj Close | AN81: Return | AP81: GSPC | AQ81: Adj Close | AR81: Return
B82: 43404 | C82: 6.883904 | E82: 43404 | F82: 4.889142 | H82: 43404 | I82: 24.28237 | K82: 43404 | L82: 47.4395 | Q82: 43404 | R82: 65.6699 | T82: 43404 | U82: 95.54681 | W82: 43404 | X82: 63.75761 | AB82: 43404 | AC82: 48.3504 | AE82: 43404 | AF82: 27.11107 | AH82: 43404 | AI82: 23.68555 | AL82: 43404 | AM82: 25.2517 | AP82: 43404 | AQ82: 2711.74
B83: 43434 | C83: 6.92028 | D83: =(C83-C82)/C82 -> 0.0052842108 | E83: 43434 | F83: 4.85467 | G83: =(F83-F82)/F82 -> -0.0070507259 | H83: 43434 | I83: 23.96814 | J83: =(I83-I82)/I82 -> -0.012940664 | K83: 43434 | L83: 46.6064 | M83: =(L83-L82)/L82 -> -0.017561315 | P83: =(S83+V83+Y83)/3 -> 0.010113431 | Q83: 43434 | R83: 66.18574 | S83: =(R83-R82)/R82 -> 0.0078550447 | T83: 43434 | U83: 102.7801 | V83: =(U83-U82)/U82 -> 0.07570415 | W83: 43434 | X83: 60.3645 | Y83: =(X83-X82)/X82 -> -0.053218902 | AA83: =(AD83+AG83+AJ83)/3 -> -0.017080732 | AB83: 43434 | AC83: 53.43484 | AD83: =(AC83-AC82)/AC82 -> 0.10515818 | AE83: 43434 | AF83: 23.48237 | AG83: =(AF83-AF82)/AF82 -> -0.13384569 | AH83: 43434 | AI83: 23.15133 | AJ83: =(AI83-AI82)/AI82 -> -0.02255468 | AL83: 43434 | AM83: 26.06065 | AN83: =(AM83-AM82)/AM82 -> 0.032035467 | AP83: 43434 | AQ83: 2760.17 | AR83: =(AQ83-AQ82)/AQ82 -> 0.017859382
B84: 43465 | C84: 7.026181 | D84: =(C84-C83)/C83 -> 0.015302994 | E84: 43465 | F84: 4.751293 | G84: =(F84-F83)/F83 -> -0.021294341 | H84: 43465 | I84: 24.2982 | J84: =(I84-I83)/I83 -> 0.013770781 | K84: 43465 | L84: 47.03952 | M84: =(L84-L83)/L83 -> 0.0092931443 | P84: =(S84+V84+Y84)/3 -> -0.095157768 | Q84: 43465 | R84: 56.76989 | S84: =(R84-R83)/R83 -> -0.14226403 | T84: 43465 | U84: 94.00917 | V84: =(U84-U83)/U83 -> -0.08533685 | W84: 43465 | X84: 56.87106 | Y84: =(X84-X83)/X83 -> -0.057872425 | AA84: =(AD84+AG84+AJ84)/3 -> -0.082211878 | AB84: 43465 | AC84: 47.5668 | AD84: =(AC84-AC83)/AC83 -> -0.10981674 | AE84: 43465 | AF84: 21.07053 | AG84: =(AF84-AF83)/AF83 -> -0.10270854 | AH84: 43465 | AI84: 22.36163 | AJ84: =(AI84-AI83)/AI83 -> -0.034110351 | AL84: 43465 | AM84: 24.91104 | AN84: =(AM84-AM83)/AM83 -> -0.044112867 | AP84: 43465 | AQ84: 2506.85 | AR84: =(AQ84-AQ83)/AQ83 -> -0.091776956
B85: 43496 | C85: 7.135304 | D85: =(C85-C84)/C84 -> 0.015530912 | E85: 43496 | F85: 4.98605 | G85: =(F85-F84)/F84 -> 0.049409077 | H85: 43496 | I85: 25.00729 | J85: =(I85-I84)/I84 -> 0.02918282 | K85: 43496 | L85: 48.14003 | M85: =(L85-L84)/L84 -> 0.023395434 | P85: =(S85+V85+Y85)/3 -> 0.071385125 | Q85: 43496 | R85: 61.00745 | S85: =(R85-R84)/R84 -> 0.074644499 | T85: 43496 | U85: 99.07301 | V85: =(U85-U84)/U84 -> 0.053865384 | W85: 43496 | X85: 61.74181 | Y85: =(X85-X84)/X84 -> 0.085645494 | AA85: =(AD85+AG85+AJ85)/3 -> 0.14658667 | AB85: 43496 | AC85: 56.89401 | AD85: =(AC85-AC84)/AC84 -> 0.19608656 | AE85: 43496 | AF85: 24.26865 | AG85: =(AF85-AF84)/AF84 -> 0.15178166 | AH85: 43496 | AI85: 24.41648 | AJ85: =(AI85-AI84)/AI84 -> 0.091891781 | AL85: 43496 | AM85: 28.43959 | AN85: =(AM85-AM84)/AM84 -> 0.14164603 | AP85: 43496 | AQ85: 2704.1 | AR85: =(AQ85-AQ84)/AQ84 -> 0.078684405
B86: 43524 | C86: 7.14269 | D86: =(C86-C85)/C85 -> 0.0010351346 | E86: 43524 | F86: 5.060894 | G86: =(F86-F85)/F85 -> 0.01501068 | H86: 43524 | I86: 25.15754 | J86: =(I86-I85)/I85 -> 0.006008248 | K86: 43524 | L86: 48.73412 | M86: =(L86-L85)/L85 -> 0.012340873 | P86: =(S86+V86+Y86)/3 -> 0.05027969 | Q86: 43524 | R86: 66.52494 | S86: =(R86-R85)/R85 -> 0.09043961 | T86: 43524 | U86: 104.3719 | V86: =(U86-U85)/U85 -> 0.053484698 | W86: 43524 | X86: 62.16874 | Y86: =(X86-X85)/X85 -> 0.0069147633 | AA86: =(AD86+AG86+AJ86)/3 -> -0.041103701 | AB86: 43524 | AC86: 48.07097 | AD86: =(AC86-AC85)/AC85 -> -0.15507854 | AE86: 43524 | AF86: 24.71501 | AG86: =(AF86-AF85)/AF85 -> 0.018392453 | AH86: 43524 | AI86: 24.74305 | AJ86: =(AI86-AI85)/AI85 -> 0.013374983 | AL86: 43524 | AM86: 28.57159 | AN86: =(AM86-AM85)/AM85 -> 0.0046414171 | AP86: 43524 | AQ86: 2784.49 | AR86: =(AQ86-AQ85)/AQ85 -> 0.02972893
B87: 43553 | C87: 7.280802 | D87: =(C87-C86)/C86 -> 0.019336132 | E87: 43553 | F87: 5.111348 | G87: =(F87-F86)/F86 -> 0.0099693849 | H87: 43553 | I87: 25.3549 | J87: =(I87-I86)/I86 -> 0.0078449642 | K87: 43553 | L87: 48.53934 | M87: =(L87-L86)/L86 -> -0.0039967891 | P87: =(S87+V87+Y87)/3 -> 0.012047566 | Q87: 43553 | R87: 68.01487 | S87: =(R87-R86)/R86 -> 0.022396563 | T87: 43553 | U87: 107.5141 | V87: =(U87-U86)/U86 -> 0.030105804 | W87: 43553 | X87: 61.15168 | Y87: =(X87-X86)/X86 -> -0.016359669 | AA87: =(AD87+AG87+AJ87)/3 -> 0.0016050625 | AB87: 43553 | AC87: 46.73078 | AD87: =(AC87-AC86)/AC86 -> -0.027879404 | AE87: 43553 | AF87: 23.71364 | AG87: =(AF87-AF86)/AF86 -> -0.040516674 | AH87: 43553 | AI87: 26.55452 | AJ87: =(AI87-AI86)/AI86 -> 0.073211265 | AL87: 43553 | AM87: 29.77092 | AN87: =(AM87-AM86)/AM86 -> 0.041976313 | AP87: 43553 | AQ87: 2834.4 | AR87: =(AQ87-AQ86)/AQ86 -> 0.017924288
B88: 43585 | C88: 7.2984 | D88: =(C88-C87)/C87 -> 0.0024170414 | E88: 43585 | F88: 5.187768 | G88: =(F88-F87)/F87 -> 0.014951046 | H88: 43585 | I88: 25.34919 | J88: =(I88-I87)/I87 -> -0.00022520302 | K88: 43585 | L88: 49.12368 | M88: =(L88-L87)/L87 -> 0.012038483 | P88: =(S88+V88+Y88)/3 -> -0.028668156 | Q88: 43585 | R88: 67.57715 | S88: =(R88-R87)/R87 -> -0.0064356515 | T88: 43585 | U88: 104.7909 | V88: =(U88-U87)/U87 -> -0.025328771 | W88: 43585 | X88: 57.83481 | Y88: =(X88-X87)/X87 -> -0.054240047 | AA88: =(AD88+AG88+AJ88)/3 -> 0.039923455 | AB88: 43585 | AC88: 49.3561 | AD88: =(AC88-AC87)/AC87 -> 0.056179674 | AE88: 43585 | AF88: 24.53777 | AG88: =(AF88-AF87)/AF87 -> 0.034753416 | AH88: 43585 | AI88: 27.32028 | AJ88: =(AI88-AI87)/AI87 -> 0.028837275 | AL88: 43585 | AM88: 29.61096 | AN88: =(AM88-AM87)/AM87 -> -0.0053730284 | AP88: 43585 | AQ88: 2945.83 | AR88: =(AQ88-AQ87)/AQ87 -> 0.039313435
B89: 43616 | C89: 7.408585 | D89: =(C89-C88)/C88 -> 0.015097145 | E89: 43616 | F89: 5.131598 | G89: =(F89-F88)/F88 -> -0.010827392 | H89: 43616 | I89: 25.07172 | J89: =(I89-I88)/I88 -> -0.010945912 | K89: 43616 | L89: 48.17899 | M89: =(L89-L88)/L88 -> -0.019230848 | P89: =(S89+V89+Y89)/3 -> -0.070668176 | Q89: 43616 | R89: 60.25477 | S89: =(R89-R88)/R88 -> -0.10835586 | T89: 43616 | U89: 100.3483 | V89: =(U89-U88)/U88 -> -0.042394903 | W89: 43616 | X89: 54.29221 | Y89: =(X89-X88)/X88 -> -0.061253767 | AA89: =(AD89+AG89+AJ89)/3 -> -0.1596295 | AB89: 43616 | AC89: 38.40752 | AD89: =(AC89-AC88)/AC88 -> -0.2218283 | AE89: 43616 | AF89: 19.75055 | AG89: =(AF89-AF88)/AF88 -> -0.19509597 | AH89: 43616 | AI89: 25.6274 | AJ89: =(AI89-AI88)/AI88 -> -0.061964226 | AL89: 43616 | AM89: 30.41077 | AN89: =(AM89-AM88)/AM88 -> 0.027010607 | AP89: 43616 | AQ89: 2752.06 | AR89: =(AQ89-AQ88)/AQ88 -> -0.065777726
B90: 43644 | C90: 7.518058 | D90: =(C90-C89)/C89 -> 0.014776506 | E90: 43644 | F90: 5.271411 | G90: =(F90-F89)/F89 -> 0.027245509 | H90: 43644 | I90: 25.90037 | J90: =(I90-I89)/I89 -> 0.033051183 | K90: 43644 | L90: 50.0781 | M90: =(L90-L89)/L89 -> 0.039417804 | P90: =(S90+V90+Y90)/3 -> 0.070140348 | Q90: 43644 | R90: 65.24407 | S90: =(R90-R89)/R89 -> 0.082803403 | T90: 43644 | U90: 109.6825 | V90: =(U90-U89)/U89 -> 0.093018018 | W90: 43644 | X90: 56.1707 | Y90: =(X90-X89)/X89 -> 0.034599623 | AA90: =(AD90+AG90+AJ90)/3 -> 0.1520627 | AB90: 43644 | AC90: 44.54535 | AD90: =(AC90-AC89)/AC89 -> 0.15980803 | AE90: 43644 | AF90: 25.00846 | AG90: =(AF90-AF89)/AF89 -> 0.26621588 | AH90: 43644 | AI90: 26.40043 | AJ90: =(AI90-AI89)/AI89 -> 0.030164199 | AL90: 43644 | AM90: 29.79291 | AN90: =(AM90-AM89)/AM89 -> -0.020317144 | AP90: 43644 | AQ90: 2941.76 | AR90: =(AQ90-AQ89)/AQ89 -> 0.068930183
B91: 43677 | C91: 7.535779 | D91: =(C91-C90)/C90 -> 0.0023571247 | E91: 43677 | F91: 5.294903 | G91: =(F91-F90)/F90 -> 0.0044564918 | H91: 43677 | I91: 25.55283 | J91: =(I91-I90)/I90 -> -0.013418341 | K91: 43677 | L91: 49.09446 | M91: =(L91-L90)/L90 -> -0.019642119 | P91: =(S91+V91+Y91)/3 -> -0.022288071 | Q91: 43677 | R91: 63.31135 | S91: =(R91-R90)/R90 -> -0.029622922 | T91: 43677 | U91: 108.5102 | V91: =(U91-U90)/U90 -> -0.010688123 | W91: 43677 | X91: 54.67919 | Y91: =(X91-X90)/X90 -> -0.026553167 | AA91: =(AD91+AG91+AJ91)/3 -> -0.072549338 | AB91: 43677 | AC91: 38.28208 | AD91: =(AC91-AC90)/AC90 -> -0.14060435 | AE91: 43677 | AF91: 24.02093 | AG91: =(AF91-AF90)/AF90 -> -0.039487837 | AH91: 43677 | AI91: 25.40894 | AJ91: =(AI91-AI90)/AI90 -> -0.037555828 | AL91: 43677 | AM91: 30.70851 | AN91: =(AM91-AM90)/AM90 -> 0.030732144 | AP91: 43677 | AQ91: 2980.38 | AR91: =(AQ91-AQ90)/AQ90 -> 0.013128195
B92: 43707 | C92: 7.710955 | D92: =(C92-C91)/C91 -> 0.023245905 | E92: 43707 | F92: 5.345647 | G92: =(F92-F91)/F91 -> 0.0095835561 | H92: 43707 | I92: 25.77771 | J92: =(I92-I91)/I91 -> 0.0088005908 | K92: 43707 | L92: 49.11394 | M92: =(L92-L91)/L91 -> 0.00039678611 | P92: =(S92+V92+Y92)/3 -> -0.07278911 | Q92: 43707 | R92: 59.02999 | S92: =(R92-R91)/R91 -> -0.067623894 | T92: 43707 | U92: 104.826 | V92: =(U92-U91)/U91 -> -0.033952569 | W92: 43707 | X92: 48.29316 | Y92: =(X92-X91)/X91 -> -0.11679087 | AA92: =(AD92+AG92+AJ92)/3 -> 0.045102442 | AB92: 43707 | AC92: 34.36021 | AD92: =(AC92-AC91)/AC91 -> -0.10244663 | AE92: 43707 | AF92: 28.01682 | AG92: =(AF92-AF91)/AF91 -> 0.16635035 | AH92: 43707 | AI92: 27.22323 | AJ92: =(AI92-AI91)/AI91 -> 0.071403608 | AL92: 43707 | AM92: 33.89516 | AN92: =(AM92-AM91)/AM91 -> 0.10377091 | AP92: 43707 | AQ92: 2926.46 | AR92: =(AQ92-AQ91)/AQ91 -> -0.018091653
B93: 43738 | C93: 7.68114 | D93: =(C93-C92)/C92 -> -0.0038665768 | E93: 43738 | F93: 5.368433 | G93: =(F93-F92)/F92 -> 0.0042625336 | H93: 43738 | I93: 25.57274 | J93: =(I93-I92)/I92 -> -0.0079514433 | K93: 43738 | L93: 48.6562 | M93: =(L93-L92)/L92 -> -0.0093199609 | P93: =(S93+V93+Y93)/3 -> 0.043523102 | Q93: 43738 | R93: 60.86604 | S93: =(R93-R92)/R92 -> 0.031103681 | T93: 43738 | U93: 105.6097 | V93: =(U93-U92)/U92 -> 0.0074761987 | W93: 43738 | X93: 52.73562 | Y93: =(X93-X92)/X92 -> 0.091989425 | AA93: =(AD93+AG93+AJ93)/3 -> 0.062331578 | AB93: 43738 | AC93: 39.20129 | AD93: =(AC93-AC92)/AC92 -> 0.14089204 | AE93: 43738 | AF93: 29.07861 | AG93: =(AF93-AF92)/AF92 -> 0.037898305 | AH93: 43738 | AI93: 27.44658 | AJ93: =(AI93-AI92)/AI92 -> 0.0082043901 | AL93: 43738 | AM93: 33.89307 | AN93: =(AM93-AM92)/AM92 -> -6.1660721e-05 | AP93: 43738 | AQ93: 2976.74 | AR93: =(AQ93-AQ92)/AQ92 -> 0.017181168
B94: 43769 | C94: 7.715867 | D94: =(C94-C93)/C93 -> 0.0045210737 | E94: 43769 | F94: 5.40135 | G94: =(F94-F93)/F93 -> 0.0061315844 | H94: 43769 | I94: 26.23465 | J94: =(I94-I93)/I93 -> 0.025883421 | K94: 43769 | L94: 49.79567 | M94: =(L94-L93)/L93 -> 0.023418804 | P94: =(S94+V94+Y94)/3 -> -0.029235912 | Q94: 43769 | R94: 58.24555 | S94: =(R94-R93)/R93 -> -0.043053401 | T94: 43769 | U94: 103.4191 | V94: =(U94-U93)/U93 -> -0.020742413 | W94: 43769 | X94: 51.47461 | Y94: =(X94-X93)/X93 -> -0.023911921 | AA94: =(AD94+AG94+AJ94)/3 -> 0.10053296 | AB94: 43769 | AC94: 45.27294 | AD94: =(AC94-AC93)/AC93 -> 0.15488393 | AE94: 43769 | AF94: 31.91598 | AG94: =(AF94-AF93)/AF93 -> 0.097575847 | AH94: 43769 | AI94: 28.79528 | AJ94: =(AI94-AI93)/AI93 -> 0.049139091 | AL94: 43769 | AM94: 36.69258 | AN94: =(AM94-AM93)/AM93 -> 0.082598301 | AP94: 43769 | AQ94: 3037.56 | AR94: =(AQ94-AQ93)/AQ93 -> 0.020431747
... B118: 44498 | C118: 8.39 | D118: =(C118-C117)/C117 -> -0.0011904762 | E118: 44498 | F118: 5.94 | G118: =(F118-F117)/F117 -> -0.0066889632 | H118: 44498 | I118: 28.3 | J118: =(I118-I117)/I117 -> 0.0060383631 | K118: 44498 | L118: 54.75 | M118: =(L118-L117)/L117 -> -0.0050881337 | P118: =(S118+V118+Y118)/3 -> 0.11011797 | Q118: 44498 | R118: 63.61506 | S118: =(R118-R117)/R117 -> 0.096055668 | T118: 44498 | U118: 113.1819 | V118: =(U118-U117)/U117 -> 0.12853609 | W118: 44498 | X118: 74.49 | Y118: =(X118-X117)/X117 -> 0.10576217 | AA118: =(AD118+AG118+AJ118)/3 -> 0.079032944 | AB118: 44498 | AC118: 80.04 | AD118: =(AC118-AC117)/AC117 -> -0.049744747 | AE118: 44498 | AF118: 56.62 | AG118: =(AF118-AF117)/AF117 -> 0.048907003 | AH118: 44498 | AI118: 66.11974 | AJ118: =(AI118-AI117)/AI117 -> 0.23793658 | AL118: 44498 | AM118: 34.33 | AN118: =(AM118-AM117)/AM117 -> 0.07180768 | AP118: 44498 | AQ118: 4605.38 | AR118: =(AQ118-AQ117)/AQ117 -> 0.069143873

Sheet Covariance Matrix
C2: Monthly Data Covariance
B4: VTI | C4: VO | D4: VB | E4: VWUSX | F4: VLUE | G4: VYM | H4: VCR | I4: VHT | J4: SCHF | K4: VWO | L4: EFG | M4: IVLU | N4: VYMI | O4: FBNDX | P4: VWEHX | Q4: PICB | R4: HYXU | S4: Oil Basket | T4: Timber Basket | U4: STOR
A5: VTI | B5: =VARP('Return Data'!$B$2:$B$37) -> 0.0029399625 | C5: 0.0031943055 | D5: 0.0034911358 | E5: 0.0031555452 | F5: 0.003187585 | G5: 0.0026208999 | H5: 0.0036342007 | I5: 0.0020939282 | J5: 0.0024279423 | K5: 0.0022414981 | L5: 0.002145571 | M5: 0.00260768 | N5: 0.0025752127 | O5: 0.00013825682 | P5: 0.0010122279 | Q5: 0.0010206453 | R5: 0.0014823791 | S5: 0.0044318829 | T5: 0.0051183607 | U5: 0.0042928636
A6: VO | B6: 0.0031943055 | C6: =VARP('Return Data'!$C$2:$C$37) -> 0.0036318278 | D6: 0.0039935896 | E6: 0.0033358837 | F6: 0.0035812369 | G6: 0.0029107983 | H6: 0.0039044542 | I6: 0.0022270112 | J6: 0.0026952811 | K6: 0.0025716989 | L6: 0.0023463558 | M6: 0.0029087765 | N6: 0.0029140593 | O6: 0.00017958648 | P6: 0.0012039867 | Q6: 0.0011544698 | R6: 0.001687281 | S6: 0.0051379556 | T6: 0.0057579985 | U6: 0.0048827946
A7: VB | B7: 0.0034911358 | C7: 0.0039935896 | D7: =VARP('Return Data'!$D$2:$D$37) -> 0.0045712912 | E7: 0.0036182057 | F7: 0.0040691587 | G7: 0.0031988761 | H7: 0.0042852364 | I7: 0.0023916538 | J7: 0.0030277633 | K7: 0.0029924154 | L7: 0.0025502879 | M7: 0.0033599947 | N7: 0.0033213128 | O7: 0.00015928698 | P7: 0.0013473567 | Q7: 0.00125815 | R7: 0.0019039492 | S7: 0.0059372776 | T7: 0.0064188252 | U7: 0.0054274784
A8: VWUSX | B8: 0.0031555452 | C8: 0.0033358837 | D8: 0.0036182057 | E8: =VARP('Return Data'!$E$2:$E$37) -> 0.0041916947 | F8: 0.0030080525 | G8: 0.0024732686 | H8: 0.0041090249 | I8: 0.0021852516 | J8: 0.002436117 | K8: 0.0023388714 | L8: 0.0023019948 | M8: 0.0023966124 | N8: 0.0024524461 | O8: 0.00024752974 | P8: 0.0010813503 | Q8: 0.0011227455 | R8: 0.0016015824 | S8: 0.0040643607 | T8: 0.0053174492 | U8: 0.0044823619
A9: VLUE | B9: 0.003187585 | C9: 0.0035812369 | D9: 0.0040691587 | E9: 0.0030080525 | F9: =VARP('Return Data'!$F$2:$F$37) -> 0.0041110391 | G9: 0.0031420522 | H9: 0.0037790804 | I9: 0.0021679851 | J9: 0.002895732 | K9: 0.0026204172 | L9: 0.0023583601 | M9: 0.003407805 | N9: 0.0032069842 | O9: 4.1978065e-05 | P9: 0.0011280129 | Q9: 0.0010231526 | R9: 0.001631928 | S9: 0.0057341039 | T9: 0.0056618642 | U9: 0.0046706588
A10: VYM | B10: 0.0026208999 | C10: 0.0029107983 | D10: 0.0031988761 | E10: 0.0024732686 | F10: 0.0031420522 | G10: =VARP('Return Data'!$G$2:$G$37) -> 0.0026015568 | H10: 0.0030881275 | I10: 0.001863354 | J10: 0.0023002388 | K10: 0.0020211092 | L10: 0.0019427107 | M10: 0.0026082964 | N10: 0.0025196427 | O10: 4.979999e-05 | P10: 0.00087383867 | Q10: 0.00084259933 | R10: 0.0012934571 | S10: 0.0045180561 | T10: 0.0044830849 | U10: 0.0037455173
A11: VCR | B11: 0.0036342007 | C11: 0.0039044542 | D11: 0.0042852364 | E11: 0.0041090249 | F11: 0.0037790804 | G11: 0.0030881275 | H11: =VARP('Return Data'!$H$2:$H$37) -> 0.004910582 | I11: 0.0025547291 | J11: 0.0029089447 | K11: 0.0028810665 | L11: 0.0025849454 | M11: 0.003050355 | N11: 0.0030870807 | O11: 0.00024201658 | P11: 0.0012906712 | Q11: 0.001366402 | R11: 0.0019463692 | S11: 0.0053891646 | T11: 0.0069236005 | U11: 0.0054814209
A12: VHT | B12: 0.0020939282 | C12: 0.0022270112 | D12: 0.0023916538 | E12: 0.0021852516 | F12: 0.0021679851 | G12: 0.001863354 | H12: 0.0025547291 | I12: =VARP('Return Data'!$I$2:$I$37) -> 0.0020878753 | J12: 0.0016307202 | K12: 0.0015589227 | L12: 0.0015516321 | M12: 0.0016533795 | N12: 0.001657406 | O12: 0.0001261412 | P12: 0.00064369711 | Q12: 0.00072322486 | R12: 0.00097262072 | S12: 0.0029534953 | T12: 0.0034929266 | U12: 0.0023510143
A13: SCHF | B13: 0.0024279423 | C13: 0.0026952811 | D13: 0.0030277633 | E13: 0.002436117 | F13: 0.002895732 | G13: 0.0023002388 | H13: 0.0029089447 | I13: 0.0016307202 | J13: =VARP('Return Data'!$J$2:$J$37) -> 0.0023559539 | K13: 0.0021061416 | L13: 0.0019913753 | M13: 0.0026398493 | N13: 0.0025632235 | O13: 0.00011256379 | P13: 0.00089100754 | Q13: 0.00094755469 | R13: 0.0014140793 | S13: 0.003990041 | T13: 0.0042915312 | U13: 0.0041292941
A14: VWO | B14: 0.0022414981 | C14: 0.0025716989 | D14: 0.0029924154 | E14: 0.0023388714 | F14: 0.0026204172 | G14: 0.0020211092 | H14: 0.0028810665 | I14: 0.0015589227 | J14: 0.0021061416 | K14: =VARP('Return Data'!$K$2:$K$37) -> 0.0026476862 | L14: 0.0017491995 | M14: 0.0022662498 | N14: 0.0024062001 | O14: 0.00015832475 | P14: 0.00098477428 | Q14: 0.0010345429 | R14: 0.0014821923 | S14: 0.0035428837 | T14: 0.0049869612 | U14: 0.0036606603
A15: EFG | B15: 0.002145571 | C15: 0.0023463558 | D15: 0.0025502879 | E15: 0.0023019948 | F15: 0.0023583601 | G15: 0.0019427107 | H15: 0.0025849454 | I15: 0.0015516321 | J15: 0.0019913753 | K15: 0.0017491995 | L15: =VARP('Return Data'!$L$2:$L$37) -> 0.0018001481 | M15: 0.0020997194 | N15: 0.0020834926 | O15: 0.00014343272 | P15: 0.00076866497 | Q15: 0.00086689372 | R15: 0.0012182831 | S15: 0.0030297885 | T15: 0.0036271834 | U15: 0.0034341616
A16: IVLU | B16: 0.00260768 | C16: 0.0029087765 | D16: 0.0033599947 | E16: 0.0023966124 | F16: 0.003407805 | G16: 0.0026082964 | H16: 0.003050355 | I16: 0.0016533795 | J16: 0.0026398493 | K16: 0.0022662498 | L16: 0.0020997194 | M16: =VARP('Return Data'!$M$2:$M$37) -> 0.0031903796 | N16: 0.0029416991 | O16: 3.6290534e-05 | P16: 0.00093115797 | Q16: 0.00089835856 | R16: 0.0014697948 | S16: 0.0050057053 | T16: 0.0045386474 | U16: 0.0045292793
A17: VYMI | B17: 0.0025752127 | C17: 0.0029140593 | D17: 0.0033213128 | E17: 0.0024524461 | F17: 0.0032069842 | G17: 0.0025196427 | H17: 0.0030870807 | I17: 0.001657406 | J17: 0.0025632235 | K17: 0.0024062001 | L17: 0.0020834926 | M17: 0.0029416991 | N17: =VARP('Return Data'!$N$2:$N$37) -> 0.0028949382 | O17: 0.00010665244 | P17: 0.00099595066 | Q17: 0.0010403371 | R17: 0.0015864294 | S17: 0.004650393 | T17: 0.0048894944 | U17: 0.0045437333
A18: FBNDX | B18: 0.00013825682 | C18: 0.00017958648 | D18: 0.00015928698 | E18: 0.00024752974 | F18: 4.1978065e-05 | G18: 4.979999e-05 | H18: 0.00024201658 | I18: 0.0001261412 | J18: 0.00011256379 | K18: 0.00015832475 | L18: 0.00014343272 | M18: 3.6290534e-05 | N18: 0.00010665244 | O18: =VARP('Return Data'!$O$2:$O$37) -> 0.00011776949 | P18: 0.00013052667 | Q18: 0.00018753707 | R18: 0.00018974179 | S18: 7.0134879e-05 | T18: 0.00048701637 | U18: 0.00052770319
A19: VWEHX | B19: 0.0010122279 | C19: 0.0012039867 | D19: 0.0013473567 | E19: 0.0010813503 | F19: 0.0011280129 | G19: 0.00087383867 | H19: 0.0012906712 | I19: 0.00064369711 | J19: 0.00089100754 | K19: 0.00098477428 | L19: 0.00076866497 | M19: 0.00093115797 | N19: 0.00099595066 | O19: 0.00013052667 | P19: =VARP('Return Data'!$P$2:$P$37) -> 0.00055450884 | Q19: 0.00050194537 | R19: 0.00070864666 | S19: 0.0014664903 | T19: 0.0022500276 | U19: 0.0017354336
A20: PICB | B20: 0.0010206453 | C20: 0.0011544698 | D20: 0.00125815 | E20: 0.0011227455 | F20: 0.0010231526 | G20: 0.00084259933 | H20: 0.001366402 | I20: 0.00072322486 | J20: 0.00094755469 | K20: 0.0010345429 | L20: 0.00086689372 | M20: 0.00089835856 | N20: 0.0010403371 | O20: 0.00018753707 | P20: 0.00050194537 | Q20: =VARP('Return Data'!$Q$2:$Q$37) -> 0.00070953978 | R20: 0.00087159193 | S20: 0.0012716809 | T20: 0.0024993778 | U20: 0.0020153883
A21: HYXU | B21: 0.0014823791 | C21: 0.001687281 | D21: 0.0019039492 | E21: 0.0016015824 | F21: 0.001631928 | G21: 0.0012934571 | H21: 0.0019463692 | I21: 0.00097262072 | J21: 0.0014140793 | K21: 0.0014821923 | L21: 0.0012182831 | M21: 0.0014697948 | N21: 0.0015864294 | O21: 0.00018974179 | P21: 0.00070864666 | Q21: 0.00087159193 | R21: =VARP('Return Data'!$R$2:$R$37) -> 0.0012153603 | S21: 0.0023159071 | T21: 0.0034615903 | U21: 0.0027223089
A22: Oil Basket | B22: 0.0044318829 | C22: 0.0051379556 | D22: 0.0059372776 | E22: 0.0040643607 | F22: 0.0057341039 | G22: 0.0045180561 | H22: 0.0053891646 | I22: 0.0029534953 | J22: 0.003990041 | K22: 0.0035428837 | L22: 0.0030297885 | M22: 0.0050057053 | N22: 0.004650393 | O22: 7.0134879e-05 | P22: 0.0014664903 | Q22: 0.0012716809 | R22: 0.0023159071 | S22: =VARP('Return Data'!$S$2:$S$37) -> 0.012284791 | T22: 0.0081818417 | U22: 0.0069069888
A23: Timber Basket | B23: 0.0051183607 | C23: 0.0057579985 | D23: 0.0064188252 | E23: 0.0053174492 | F23: 0.0056618642 | G23: 0.0044830849 | H23: 0.0069236005 | I23: 0.0034929266 | J23: 0.0042915312 | K23: 0.0049869612 | L23: 0.0036271834 | M23: 0.0045386474 | N23: 0.0048894944 | O23: 0.00048701637 | P23: 0.0022500276 | Q23: 0.0024993778 | R23: 0.0034615903 | S23: 0.0081818417 | T23: =VARP('Return Data'!$T$2:$T$37) -> 0.013577503 | U23: 0.008152922
A24: STOR | B24: 0.0042928636 | C24: 0.0048827946 | D24: 0.0054274784 | E24: 0.0044823619 | F24: 0.0046706588 | G24: 0.0037455173 | H24: 0.0054814209 | I24: 0.0023510143 | J24: 0.0041292941 | K24: 0.0036606603 | L24: 0.0034341616 | M24: 0.0045292793 | N24: 0.0045437333 | O24: 0.00052770319 | P24: 0.0017354336 | Q24: 0.0020153883 | R24: 0.0027223089 | S24: 0.0069069888 | T24: 0.008152922 | U24: =VARP('Return Data'!$U$2:$U$37) -> 0.013197632
C26: Annualized data 'S'
B28: VTI | C28: VO | D28: VB | E28: VWUSX | F28: VLUE | G28: VYM | H28: VCR | I28: VHT | J28: SCHF | K28: VWO | L28: EFG | M28: IVLU | N28: VYMI | O28: FBNDX | P28: VWEHX | Q28: PICB | R28: HYXU | S28: Oil Basket | T28: Timber Basket | U28: STOR
A29: VTI | B29: =B5*12 -> 0.03527955 | C29: =C5*12 -> 0.038331665 | D29: =D5*12 -> 0.04189363 | E29: =E5*12 -> 0.037866543 | F29: =F5*12 -> 0.03825102 | G29: =G5*12 -> 0.031450799 | H29: =H5*12 -> 0.043610409 | I29: =I5*12 -> 0.025127138 | ... U29: =U5*12 -> 0.051514363
A30: VO | B30: =B6*12 -> 0.038331665 | C30: =C6*12 -> 0.043581934 | D30: =D6*12 -> 0.047923075 | E30: =E6*12 -> 0.040030604 | F30: =F6*12 -> 0.042974843 | G30: =G6*12 -> 0.03492958 | H30: =H6*12 -> 0.046853451 | I30: =I6*12 -> 0.026724135 | ... U30: =U6*12 -> 0.058593535
A31: VB | B31: =B7*12 -> 0.04189363 | C31: =C7*12 -> 0.047923075 | D31: =D7*12 -> 0.054855494 | E31: =E7*12 -> 0.043418469 | F31: =F7*12 -> 0.048829905 | G31: =G7*12 -> 0.038386513 | H31: =H7*12 -> 0.051422836 | I31: =I7*12 -> 0.028699845 | ... U31: =U7*12 -> 0.065129741
A32: VWUSX | B32: =B8*12 -> 0.037866543 | C32: =C8*12 -> 0.040030604 | D32: =D8*12 -> 0.043418469 | E32: =E8*12 -> 0.050300337 | F32: =F8*12 -> 0.03609663 | G32: =G8*12 -> 0.029679223 | H32: =H8*12 -> 0.049308299 | I32: =I8*12 -> 0.02622302 | ... U32: =U8*12 -> 0.053788343
A33: VLUE | B33: =B9*12 -> 0.03825102 | C33: =C9*12 -> 0.042974843 | D33: =D9*12 -> 0.048829905 | E33: =E9*12 -> 0.03609663 | F33: =F9*12 -> 0.049332469 | G33: =G9*12 -> 0.037704626 | H33: =H9*12 -> 0.045348965 | I33: =I9*12 -> 0.026015821 | ... U33: =U9*12 -> 0.056047905
A34: VYM | B34: =B10*12 -> 0.031450799 | C34: =C10*12 -> 0.03492958 | D34: =D10*12 -> 0.038386513 | E34: =E10*12 -> 0.029679223 | F34: =F10*12 -> 0.037704626 | G34: =G10*12 -> 0.031218682 | H34: =H10*12 -> 0.03705753 | I34: =I10*12 -> 0.022360248 | ... U34: =U10*12 -> 0.044946207
A35: VCR | B35: =B11*12 -> 0.043610409 | C35: =C11*12 -> 0.046853451 | D35: =D11*12 -> 0.051422836 | E35: =E11*12 -> 0.049308299 | F35: =F11*12 -> 0.045348965 | G35: =G11*12 -> 0.03705753 | H35: =H11*12 -> 0.058926984 | I35: =I11*12 -> 0.03065675 | ... U35: =U11*12 -> 0.065777051
A36: VHT | B36: =B12*12 -> 0.025127138 | C36: =C12*12 -> 0.026724135 | D36: =D12*12 -> 0.028699845 | E36: =E12*12 -> 0.02622302 | F36: =F12*12 -> 0.026015821 | G36: =G12*12 -> 0.022360248 | H36: =H12*12 -> 0.03065675 | I36: =I12*12 -> 0.025054504 | ... U36: =U12*12 -> 0.028212172
A37: SCHF | B37: =B13*12 -> 0.029135307 | C37: =C13*12 -> 0.032343374 | D37: =D13*12 -> 0.03633316 | E37: =E13*12 -> 0.029233404 | F37: =F13*12 -> 0.034748784 | G37: =G13*12 -> 0.027602866 | H37: =H13*12 -> 0.034907337 | I37: =I13*12 -> 0.019568642 | ... U37: =U13*12 -> 0.049551529
A38: VWO | B38: =B14*12 -> 0.026897978 | C38: =C14*12 -> 0.030860386 | D38: =D14*12 -> 0.035908984 | E38: =E14*12 -> 0.028066456 | F38: =F14*12 -> 0.031445007 | G38: =G14*12 -> 0.02425331 | H38: =H14*12 -> 0.034572798 | I38: =I14*12 -> 0.018707073 | ... U38: =U14*12 -> 0.043927924
A39: EFG | B39: =B15*12 -> 0.025746851 | C39: =C15*12 -> 0.028156269 | D39: =D15*12 -> 0.030603455 | E39: =E15*12 -> 0.027623938 | F39: =F15*12 -> 0.028300321 | G39: =G15*12 -> 0.023312528 | H39: =H15*12 -> 0.031019345 | I39: =I15*12 -> 0.018619586 | ... U39: =U15*12 -> 0.04120994
A40: IVLU | B40: =B16*12 -> 0.03129216 | C40: =C16*12 -> 0.034905318 | D40: =D16*12 -> 0.040319936 | E40: =E16*12 -> 0.028759349 | F40: =F16*12 -> 0.04089366 | G40: =G16*12 -> 0.031299557 | H40: =H16*12 -> 0.03660426 | I40: =I16*12 -> 0.019840554 | ... U40: =U16*12 -> 0.054351352
... A48: STOR | B48: =B24*12 -> 0.051514363 | C48: =C24*12 -> 0.058593535 | D48: =D24*12 -> 0.065129741 | E48: =E24*12 -> 0.053788343 | F48: =F24*12 -> 0.056047905 | G48: =G24*12 -> 0.044946207 | H48: =H24*12 -> 0.065777051 | I48: =I24*12 -> 0.028212172 | ... U48: =U24*12 -> 0.15837159
C50: Shrinkage target 'F'
B52: VTI | C52: VO | D52: VB | E52: VWUSX | F52: VLUE | G52: VYM | H52: VCR | I52: VHT | J52: SCHF | K52: VWO | L52: EFG | M52: IVLU | N52: VYMI | O52: FBNDX | P52: VWEHX | Q52: PICB | R52: HYXU | S52: Oil Basket | T52: Timber Basket | U52: STOR
A53: VTI | B53: =B29*1.25 -> 0.044099437 | C53: 0.053868108 | D53: 0.060435002 | E53: 0.05787139 | F53: 0.057311912 | G53: 0.045591696 | H53: 0.062637668 | I53: 0.040843352 | J53: 0.047843096 | K53: 0.045994124 | L53: 0.037924792 | M53: 0.050488245 | N53: 0.048093761 | O53: 0.0097003072 | P53: 0.021048606 | Q53: 0.023809894 | R53: 0.031161735 | S53: 0.09907247 | T53: 0.10415474 | U53: 0.10268739
A54: VO | B54: =1.25*MAX(B30,0,'Correlation Matrix'!$B$44*SQRT('Covariance Matrix'!$B$53*C54)) -> 0.053868108 | C54: =C30*1.25 -> 0.054477417 | D54: 0.067170761 | E54: 0.064321424 | F54: 0.063699589 | G54: 0.050673101 | H54: 0.069618924 | I54: 0.045395531 | J54: 0.053175429 | K54: 0.051120381 | L54: 0.042151685 | M54: 0.056115392 | N54: 0.053454032 | O54: 0.010781451 | P54: 0.02339457 | Q54: 0.026463617 | R54: 0.034634853 | S54: 0.11011455 | T54: 0.11576327 | U54: 0.11413237
A55: VB | B55: =1.25*MAX(B31,0,'Correlation Matrix'!$B$44*SQRT('Covariance Matrix'!$B$53*D55)) -> 0.060435002 | C55: =1.25*MAX(C31,0,'Correlation Matrix'!$B$44*SQRT('Covariance Matrix'!$C$54*D55)) -> 0.067170761 | D55: =D31*1.25 -> 0.068569368 | E55: 0.072162649 | F55: 0.071465008 | G55: 0.056850502 | H55: 0.078105951 | I55: 0.05092956 | J55: 0.059657881 | K55: 0.057352308 | L55: 0.047290266 | M55: 0.062956246 | N55: 0.059970447 | O55: 0.012095784 | P55: 0.026246529 | Q55: 0.029689714 | R55: 0.038857081 | S55: 0.12353828 | T55: 0.12987561 | U55: 0.12804589
A56: VWUSX | B56: =1.25*MAX(B32,0,'Correlation Matrix'!$B$44*SQRT('Covariance Matrix'!$B$53*E56)) -> 0.05787139 | C56: =1.25*MAX(C32,0,'Correlation Matrix'!$B$44*SQRT('Covariance Matrix'!$C$54*E56)) -> 0.064321424 | D56: =1.25*MAX(D32,0,'Correlation Matrix'!$B$44*SQRT('Covariance Matrix'!$D$55*E56)) -> 0.072162649 | E56: =E32*1.25 -> 0.062875421 | F56: 0.068433511 | G56: 0.054438942 | H56: 0.074792751 | I56: 0.048769163 | J56: 0.057127235 | K56: 0.054919462 | L56: 0.045284246 | M56: 0.060285685 | N56: 0.057426542 | O56: 0.01158269 | P56: 0.025133169 | Q56: 0.028430297 | R56: 0.03720879 | S56: 0.11829787 | T56: 0.12436638 | U56: 0.12261427
A57: VLUE | B57: =1.25*MAX(B33,0,'Correlation Matrix'!$B$44*SQRT('Covariance Matrix'!$B$53*F57)) -> 0.057311912 | C57: =1.25*MAX(C33,0,'Correlation Matrix'!$B$44*SQRT('Covariance Matrix'!$C$54*F57)) -> 0.063699589 | D57: =1.25*MAX(D33,0,'Correlation Matrix'!$B$44*SQRT('Covariance Matrix'!$D$55*F57)) -> 0.071465008 | E57: =1.25*MAX(E33,0,'Correlation Matrix'!$B$44*SQRT('Covariance Matrix'!$E$56*F57)) -> 0.068433511 | F57: =F33*1.25 -> 0.061665586 | G57: 0.053912648 | H57: 0.074069683 | I57: 0.048297681 | J57: 0.056574951 | K57: 0.054388522 | L57: 0.044846455 | M57: 0.059702866 | N57: 0.056871364 | O57: 0.011470713 | P57: 0.024890192 | Q57: 0.028155444 | R57: 0.03684907 | S57: 0.11715421 | T57: 0.12316405 | U57: 0.12142889
A58: VYM | B58: =1.25*MAX(B34,0,'Correlation Matrix'!$B$44*SQRT('Covariance Matrix'!$B$53*G58)) -> 0.045591696 | C58: =1.25*MAX(C34,0,'Correlation Matrix'!$B$44*SQRT('Covariance Matrix'!$C$54*G58)) -> 0.050673101 | D58: =1.25*MAX(D34,0,'Correlation Matrix'!$B$44*SQRT('Covariance Matrix'!$D$55*G58)) -> 0.056850502 | E58: =1.25*MAX(E34,0,'Correlation Matrix'!$B$44*SQRT('Covariance Matrix'!$E$56*G58)) -> 0.054438942 | F58: =1.25*MAX(F34,0,'Correlation Matrix'!$B$44*SQRT('Covariance Matrix'!$F$57*G58)) -> 0.053912648 | G58: =G34*1.25 -> 0.039023352 | H58: 0.058922524 | I58: 0.038420865 | J58: 0.045005443 | K58: 0.043266136 | L58: 0.03567541 | M58: 0.047493703 | N58: 0.04524124 | O58: 0.0091249659 | P58: 0.019800178 | Q58: 0.02239769 | R58: 0.02931348 | S58: 0.093196317 | T58: 0.097977153 | U58: 0.096596829
A59: VCR | B59: =1.25*MAX(B35,0,'Correlation Matrix'!$B$44*SQRT('Covariance Matrix'!$B$53*H59)) -> 0.062637668 | C59: =1.25*MAX(C35,0,'Correlation Matrix'!$B$44*SQRT('Covariance Matrix'!$C$54*H59)) -> 0.069618924 | D59: =1.25*MAX(D35,0,'Correlation Matrix'!$B$44*SQRT('Covariance Matrix'!$D$55*H59)) -> 0.078105951 | E59: =1.25*MAX(E35,0,'Correlation Matrix'!$B$44*SQRT('Covariance Matrix'!$E$56*H59)) -> 0.074792751 | F59: =1.25*MAX(F35,0,'Correlation Matrix'!$B$44*SQRT('Covariance Matrix'!$F$57*H59)) -> 0.074069683 | G59: =1.25*MAX(G35,0,'Correlation Matrix'!$B$44*SQRT('Covariance Matrix'!$G$58*H59)) -> 0.058922524 | H59: =H35*1.25 -> 0.07365873 | I59: 0.052785782 | J59: 0.061832224 | K59: 0.059442619 | L59: 0.049013848 | M59: 0.065250803 | N59: 0.062156182 | O59: 0.012536638 | P59: 0.027203133 | Q59: 0.030771811 | R59: 0.0402733 | S59: 0.12804086 | T59: 0.13460917 | U59: 0.13271276
A60: VHT | B60: =1.25*MAX(B36,0,'Correlation Matrix'!$B$44*SQRT('Covariance Matrix'!$B$53*I60)) -> 0.040843352 | C60: =1.25*MAX(C36,0,'Correlation Matrix'!$B$44*SQRT('Covariance Matrix'!$C$54*I60)) -> 0.045395531 | D60: =1.25*MAX(D36,0,'Correlation Matrix'!$B$44*SQRT('Covariance Matrix'!$D$55*I60)) -> 0.05092956 | E60: =1.25*MAX(E36,0,'Correlation Matrix'!$B$44*SQRT('Covariance Matrix'!$E$56*I60)) -> 0.048769163 | F60: =1.25*MAX(F36,0,'Correlation Matrix'!$B$44*SQRT('Covariance Matrix'!$F$57*I60)) -> 0.048297681 | G60: =1.25*MAX(G36,0,'Correlation Matrix'!$B$44*SQRT('Covariance Matrix'!$G$58*I60)) -> 0.038420865 | H60: =1.25*MAX(H36,0,'Correlation Matrix'!$B$44*SQRT('Covariance Matrix'!$H$59*I60)) -> 0.052785782 | I60: =I36*1.25 -> 0.031318129 | J60: 0.040318156 | K60: 0.038759997 | L60: 0.03195984 | M60: 0.042547266 | N60: 0.040529395 | O60: 0.0081746068 | P60: 0.017738003 | Q60: 0.020064986 | R60: 0.026260501 | S60: 0.083489983 | T60: 0.087772898 | U60: 0.086536333
A61: SCHF | B61: =1.25*MAX(B37,0,'Correlation Matrix'!$B$44*SQRT('Covariance Matrix'!$B$53*J61)) -> 0.047843096 | C61: =1.25*MAX(C37,0,'Correlation Matrix'!$B$44*SQRT('Covariance Matrix'!$C$54*J61)) -> 0.053175429 | D61: =1.25*MAX(D37,0,'Correlation Matrix'!$B$44*SQRT('Covariance Matrix'!$D$55*J61)) -> 0.059657881 | E61: =1.25*MAX(E37,0,'Correlation Matrix'!$B$44*SQRT('Covariance Matrix'!$E$56*J61)) -> 0.057127235 | F61: =1.25*MAX(F37,0,'Correlation Matrix'!$B$44*SQRT('Covariance Matrix'!$F$57*J61)) -> 0.056574951 | G61: =1.25*MAX(G37,0,'Correlation Matrix'!$B$44*SQRT('Covariance Matrix'!$G$58*J61)) -> 0.045005443 | H61: =1.25*MAX(H37,0,'Correlation Matrix'!$B$44*SQRT('Covariance Matrix'!$H$59*J61)) -> 0.061832224 | I61: =1.25*MAX(I37,0,'Correlation Matrix'!$B$44*SQRT('Covariance Matrix'!$I$60*J61)) -> 0.040318156 | J61: =J37*1.52 -> 0.042972599 | K61: 0.045402695 | L61: 0.037437126 | M61: 0.049839027 | N61: 0.047475334 | O61: 0.0095755731 | P61: 0.020777946 | Q61: 0.023503728 | R61: 0.030761033 | S61: 0.097798518 | T61: 0.10281544 | U61: 0.10136695
A62: VWO | B62: =1.25*MAX(B38,0,'Correlation Matrix'!$B$44*SQRT('Covariance Matrix'!$B$53*K62)) -> 0.045994124 | C62: =1.25*MAX(C38,0,'Correlation Matrix'!$B$44*SQRT('Covariance Matrix'!$C$54*K62)) -> 0.051120381 | D62: =1.25*MAX(D38,0,'Correlation Matrix'!$B$44*SQRT('Covariance Matrix'!$D$55*K62)) -> 0.057352308 | E62: =1.25*MAX(E38,0,'Correlation Matrix'!$B$44*SQRT('Covariance Matrix'!$E$56*K62)) -> 0.054919462 | F62: =1.25*MAX(F38,0,'Correlation Matrix'!$B$44*SQRT('Covariance Matrix'!$F$57*K62)) -> 0.054388522 | G62: =1.25*MAX(G38,0,'Correlation Matrix'!$B$44*SQRT('Covariance Matrix'!$G$58*K62)) -> 0.043266136 | H62: =1.25*MAX(H38,0,'Correlation Matrix'!$B$44*SQRT('Covariance Matrix'!$H$59*K62)) -> 0.059442619 | I62: =1.25*MAX(I38,0,'Correlation Matrix'!$B$44*SQRT('Covariance Matrix'!$I$60*K62)) -> 0.038759997 | J62: =1.25*MAX(J38,0,'Correlation Matrix'!$B$44*SQRT('Covariance Matrix'!$J$61*K62)) -> 0.045402695 | K62: =K38*1.25 -> 0.039715293 | L62: 0.035990309 | M62: 0.047912919 | N62: 0.045640574 | O62: 0.0092055098 | P62: 0.019974949 | Q62: 0.022595389 | R62: 0.029572224 | S62: 0.094018939 | T62: 0.098841975 | U62: 0.097449466
A63: EFG | B63: =1.25*MAX(B39,0,'Correlation Matrix'!$B$44*SQRT('Covariance Matrix'!$B$53*L63)) -> 0.037924792 | C63: =1.25*MAX(C39,0,'Correlation Matrix'!$B$44*SQRT('Covariance Matrix'!$C$54*L63)) -> 0.042151685 | D63: =1.25*MAX(D39,0,'Correlation Matrix'!$B$44*SQRT('Covariance Matrix'!$D$55*L63)) -> 0.047290266 | E63: =1.25*MAX(E39,0,'Correlation Matrix'!$B$44*SQRT('Covariance Matrix'!$E$56*L63)) -> 0.045284246 | F63: =1.25*MAX(F39,0,'Correlation Matrix'!$B$44*SQRT('Covariance Matrix'!$F$57*L63)) -> 0.044846455 | G63: =1.25*MAX(G39,0,'Correlation Matrix'!$B$44*SQRT('Covariance Matrix'!$G$58*L63)) -> 0.03567541 | H63: =1.25*MAX(H39,0,'Correlation Matrix'!$B$44*SQRT('Covariance Matrix'!$H$59*L63)) -> 0.049013848 | I63: =1.25*MAX(I39,0,'Correlation Matrix'!$B$44*SQRT('Covariance Matrix'!$I$60*L63)) -> 0.03195984 | J63: =1.25*MAX(J39,0,'Correlation Matrix'!$B$44*SQRT('Covariance Matrix'!$J$61*L63)) -> 0.037437126 | K63: =1.25*MAX(K39,0,'Correlation Matrix'!$B$44*SQRT('Covariance Matrix'!$K$62*L63)) -> 0.035990309 | L63: =L39*1.25 -> 0.027002221 | M63: 0.039506949 | N63: 0.03763327 | O63: 0.0075904707 | P63: 0.016470491 | Q63: 0.018631194 | R63: 0.024383994 | S63: 0.077524007 | T63: 0.081500876 | U63: 0.080352673
A64: IVLU | B64: =1.25*MAX(B40,0,'Correlation Matrix'!$B$44*SQRT('Covariance Matrix'!$B$53*M64)) -> 0.050488245 | C64: =1.25*MAX(C40,0,'Correlation Matrix'!$B$44*SQRT('Covariance Matrix'!$C$54*M64)) -> 0.056115392 | D64: =1.25*MAX(D40,0,'Correlation Matrix'!$B$44*SQRT('Covariance Matrix'!$D$55*M64)) -> 0.062956246 | E64: =1.25*MAX(E40,0,'Correlation Matrix'!$B$44*SQRT('Covariance Matrix'!$E$56*M64)) -> 0.060285685 | F64: =1.25*MAX(F40,0,'Correlation Matrix'!$B$44*SQRT('Covariance Matrix'!$F$57*M64)) -> 0.059702866 | G64: =1.25*MAX(G40,0,'Correlation Matrix'!$B$44*SQRT('Covariance Matrix'!$G$58*M64)) -> 0.047493703 | H64: =1.25*MAX(H40,0,'Correlation Matrix'!$B$44*SQRT('Covariance Matrix'!$H$59*M64)) -> 0.065250803 | I64: =1.25*MAX(I40,0,'Correlation Matrix'!$B$44*SQRT('Covariance Matrix'!$I$60*M64)) -> 0.042547266 | J64: =1.25*MAX(J40,0,'Correlation Matrix'!$B$44*SQRT('Covariance Matrix'!$J$61*M64)) -> 0.049839027 | K64: =1.25*MAX(K40,0,'Correlation Matrix'!$B$44*SQRT('Covariance Matrix'!$K$62*M64)) -> 0.047912919 | L64: =1.25*MAX(L40,0,'Correlation Matrix'!$B$44*SQRT('Covariance Matrix'!$L$63*M64)) -> 0.039506949 | M64: =M40*1.25 -> 0.047855694 | N64: 0.05010015 | O64: 0.010104987 | P64: 0.021926717 | Q64: 0.024803202 | R64: 0.032461748 | S64: 0.1032056 | T64: 0.1084999 | U64: 0.10697133
A65: VYMI | B65: =1.25*MAX(B41,0,'Correlation Matrix'!$B$44*SQRT('Covariance Matrix'!$B$53*N65)) -> 0.048093761 | C65: =1.25*MAX(C41,0,'Correlation Matrix'!$B$44*SQRT('Covariance Matrix'!$C$54*N65)) -> 0.053454032 | D65: =1.25*MAX(D41,0,'Correlation Matrix'!$B$44*SQRT('Covariance Matrix'!$D$55*N65)) -> 0.059970447 | E65: =1.25*MAX(E41,0,'Correlation Matrix'!$B$44*SQRT('Covariance Matrix'!$E$56*N65)) -> 0.057426542 | F65: =1.25*MAX(F41,0,'Correlation Matrix'!$B$44*SQRT('Covariance Matrix'!$F$57*N65)) -> 0.056871364 | G65: =1.25*MAX(G41,0,'Correlation Matrix'!$B$44*SQRT('Covariance Matrix'!$G$58*N65)) -> 0.04524124 | H65: =1.25*MAX(H41,0,'Correlation Matrix'!$B$44*SQRT('Covariance Matrix'!$H$59*N65)) -> 0.062156182 | I65: =1.25*MAX(I41,0,'Correlation Matrix'!$B$44*SQRT('Covariance Matrix'!$I$60*N65)) -> 0.040529395 | J65: =1.25*MAX(J41,0,'Correlation Matrix'!$B$44*SQRT('Covariance Matrix'!$J$61*N65)) -> 0.047475334 | K65: =1.25*MAX(K41,0,'Correlation Matrix'!$B$44*SQRT('Covariance Matrix'!$K$62*N65)) -> 0.045640574 | L65: =1.25*MAX(L41,0,'Correlation Matrix'!$B$44*SQRT('Covariance Matrix'!$L$63*N65)) -> 0.03763327 | M65: =1.25*MAX(M41,0,'Correlation Matrix'!$B$44*SQRT('Covariance Matrix'!$M$64*N65)) -> 0.05010015 | N65: =N41*1.25 -> 0.043424072 | O65: 0.0096257425 | P65: 0.020886808 | Q65: 0.023626871 | R65: 0.030922199 | S65: 0.098310915 | T65: 0.10335412 | U65: 0.10189805
A66: FBNDX | B66: =1.25*MAX(B42,0,'Correlation Matrix'!$B$44*SQRT('Covariance Matrix'!$B$53*O66)) -> 0.0097003072 | C66: =1.25*MAX(C42,0,'Correlation Matrix'!$B$44*SQRT('Covariance Matrix'!$C$54*O66)) -> 0.010781451 | D66: =1.25*MAX(D42,0,'Correlation Matrix'!$B$44*SQRT('Covariance Matrix'!$D$55*O66)) -> 0.012095784 | E66: =1.25*MAX(E42,0,'Correlation Matrix'!$B$44*SQRT('Covariance Matrix'!$E$56*O66)) -> 0.01158269 | F66: =1.25*MAX(F42,0,'Correlation Matrix'!$B$44*SQRT('Covariance Matrix'!$F$57*O66)) -> 0.011470713 | G66: =1.25*MAX(G42,0,'Correlation Matrix'!$B$44*SQRT('Covariance Matrix'!$G$58*O66)) -> 0.0091249659 | H66: =1.25*MAX(H42,0,'Correlation Matrix'!$B$44*SQRT('Covariance Matrix'!$H$59*O66)) -> 0.012536638 | I66: =1.25*MAX(I42,0,'Correlation Matrix'!$B$44*SQRT('Covariance Matrix'!$I$60*O66)) -> 0.0081746068 | J66: =1.25*MAX(J42,0,'Correlation Matrix'!$B$44*SQRT('Covariance Matrix'!$J$61*O66)) -> 0.0095755731 | K66: =1.25*MAX(K42,0,'Correlation Matrix'!$B$44*SQRT('Covariance Matrix'!$K$62*O66)) -> 0.0092055098 | L66: =1.25*MAX(L42,0,'Correlation Matrix'!$B$44*SQRT('Covariance Matrix'!$L$63*O66)) -> 0.0075904707 | M66: =1.25*MAX(M42,0,'Correlation Matrix'!$B$44*SQRT('Covariance Matrix'!$M$64*O66)) -> 0.010104987 | N66: =1.25*MAX(N42,0,'Correlation Matrix'!$B$44*SQRT('Covariance Matrix'!$N$65*O66)) -> 0.0096257425 | O66: =O42*1.25 -> 0.0017665423 | P66: 0.0042127805 | Q66: 0.0047654396 | R66: 0.0062368762 | S66: 0.019828894 | T66: 0.020846087 | U66: 0.020552403
A67: VWEHX | B67: =1.25*MAX(B43,0,'Correlation Matrix'!$B$44*SQRT('Covariance Matrix'!$B$53*P67)) -> 0.021048606 | C67: =1.25*MAX(C43,0,'Correlation Matrix'!$B$44*SQRT('Covariance Matrix'!$C$54*P67)) -> 0.02339457 | D67: =1.25*MAX(D43,0,'Correlation Matrix'!$B$44*SQRT('Covariance Matrix'!$D$55*P67)) -> 0.026246529 | E67: =1.25*MAX(E43,0,'Correlation Matrix'!$B$44*SQRT('Covariance Matrix'!$E$56*P67)) -> 0.025133169 | F67: =1.25*MAX(F43,0,'Correlation Matrix'!$B$44*SQRT('Covariance Matrix'!$F$57*P67)) -> 0.024890192 | G67: =1.25*MAX(G43,0,'Correlation Matrix'!$B$44*SQRT('Covariance Matrix'!$G$58*P67)) -> 0.019800178 | H67: =1.25*MAX(H43,0,'Correlation Matrix'!$B$44*SQRT('Covariance Matrix'!$H$59*P67)) -> 0.027203133 | I67: =1.25*MAX(I43,0,'Correlation Matrix'!$B$44*SQRT('Covariance Matrix'!$I$60*P67)) -> 0.017738003 | J67: =1.25*MAX(J43,0,'Correlation Matrix'!$B$44*SQRT('Covariance Matrix'!$J$61*P67)) -> 0.020777946 | K67: =1.25*MAX(K43,0,'Correlation Matrix'!$B$44*SQRT('Covariance Matrix'!$K$62*P67)) -> 0.019974949 | L67: =1.25*MAX(L43,0,'Correlation Matrix'!$B$44*SQRT('Covariance Matrix'!$L$63*P67)) -> 0.016470491 | M67: =1.25*MAX(M43,0,'Correlation Matrix'!$B$44*SQRT('Covariance Matrix'!$M$64*P67)) -> 0.021926717 | N67: =1.25*MAX(N43,0,'Correlation Matrix'!$B$44*SQRT('Covariance Matrix'!$N$65*P67)) -> 0.020886808 | O67: =1.25*MAX(O43,0,'Correlation Matrix'!$B$44*SQRT('Covariance Matrix'!$O$66*P67)) -> 0.0042127805 | P67: =P43*1.25 -> 0.0083176326 | Q67: 0.010340483 | R67: 0.013533339 | S67: 0.043026531 | T67: 0.045233729 | U67: 0.044596466
A68: PICB | B68: =1.25*MAX(B44,0,'Correlation Matrix'!$B$44*SQRT('Covariance Matrix'!$B$53*Q68)) -> 0.023809894 | C68: =1.25*MAX(C44,0,'Correlation Matrix'!$B$44*SQRT('Covariance Matrix'!$C$54*Q68)) -> 0.026463617 | D68: =1.25*MAX(D44,0,'Correlation Matrix'!$B$44*SQRT('Covariance Matrix'!$D$55*Q68)) -> 0.029689714 | E68: =1.25*MAX(E44,0,'Correlation Matrix'!$B$44*SQRT('Covariance Matrix'!$E$56*Q68)) -> 0.028430297 | F68: =1.25*MAX(F44,0,'Correlation Matrix'!$B$44*SQRT('Covariance Matrix'!$F$57*Q68)) -> 0.028155444 | G68: =1.25*MAX(G44,0,'Correlation Matrix'!$B$44*SQRT('Covariance Matrix'!$G$58*Q68)) -> 0.02239769 | H68: =1.25*MAX(H44,0,'Correlation Matrix'!$B$44*SQRT('Covariance Matrix'!$H$59*Q68)) -> 0.030771811 | I68: =1.25*MAX(I44,0,'Correlation Matrix'!$B$44*SQRT('Covariance Matrix'!$I$60*Q68)) -> 0.020064986 | J68: =1.25*MAX(J44,0,'Correlation Matrix'!$B$44*SQRT('Covariance Matrix'!$J$61*Q68)) -> 0.023503728 | K68: =1.25*MAX(K44,0,'Correlation Matrix'!$B$44*SQRT('Covariance Matrix'!$K$62*Q68)) -> 0.022595389 | L68: =1.25*MAX(L44,0,'Correlation Matrix'!$B$44*SQRT('Covariance Matrix'!$L$63*Q68)) -> 0.018631194 | M68: =1.25*MAX(M44,0,'Correlation Matrix'!$B$44*SQRT('Covariance Matrix'!$M$64*Q68)) -> 0.024803202 | N68: =1.25*MAX(N44,0,'Correlation Matrix'!$B$44*SQRT('Covariance Matrix'!$N$65*Q68)) -> 0.023626871 | O68: =1.25*MAX(O44,0,'Correlation Matrix'!$B$44*SQRT('Covariance Matrix'!$O$66*Q68)) -> 0.0047654396 | P68: =1.25*MAX(P44,0,'Correlation Matrix'!$B$44*SQRT('Covariance Matrix'!$P$67*Q68)) -> 0.010340483 | Q68: =Q44*1.25 -> 0.010643097 | R68: 0.015308728 | S68: 0.048671022 | T68: 0.051167775 | U68: 0.050446912
A69: HYXU | B69: =1.25*MAX(B45,0,'Correlation Matrix'!$B$44*SQRT('Covariance Matrix'!$B$53*R69)) -> 0.031161735 | C69: =1.25*MAX(C45,0,'Correlation Matrix'!$B$44*SQRT('Covariance Matrix'!$C$54*R69)) -> 0.034634853 | D69: =1.25*MAX(D45,0,'Correlation Matrix'!$B$44*SQRT('Covariance Matrix'!$D$55*R69)) -> 0.038857081 | E69: =1.25*MAX(E45,0,'Correlation Matrix'!$B$44*SQRT('Covariance Matrix'!$E$56*R69)) -> 0.03720879 | F69: =1.25*MAX(F45,0,'Correlation Matrix'!$B$44*SQRT('Covariance Matrix'!$F$57*R69)) -> 0.03684907 | G69: =1.25*MAX(G45,0,'Correlation Matrix'!$B$44*SQRT('Covariance Matrix'!$G$58*R69)) -> 0.02931348 | H69: =1.25*MAX(H45,0,'Correlation Matrix'!$B$44*SQRT('Covariance Matrix'!$H$59*R69)) -> 0.0402733 | I69: =1.25*MAX(I45,0,'Correlation Matrix'!$B$44*SQRT('Covariance Matrix'!$I$60*R69)) -> 0.026260501 | J69: =1.25*MAX(J45,0,'Correlation Matrix'!$B$44*SQRT('Covariance Matrix'!$J$61*R69)) -> 0.030761033 | K69: =1.25*MAX(K45,0,'Correlation Matrix'!$B$44*SQRT('Covariance Matrix'!$K$62*R69)) -> 0.029572224 | L69: =1.25*MAX(L45,0,'Correlation Matrix'!$B$44*SQRT('Covariance Matrix'!$L$63*R69)) -> 0.024383994 | M69: =1.25*MAX(M45,0,'Correlation Matrix'!$B$44*SQRT('Covariance Matrix'!$M$64*R69)) -> 0.032461748 | N69: =1.25*MAX(N45,0,'Correlation Matrix'!$B$44*SQRT('Covariance Matrix'!$N$65*R69)) -> 0.030922199 | O69: =1.25*MAX(O45,0,'Correlation Matrix'!$B$44*SQRT('Covariance Matrix'!$O$66*R69)) -> 0.0062368762 | P69: =1.25*MAX(P45,0,'Correlation Matrix'!$B$44*SQRT('Covariance Matrix'!$P$67*R69)) -> 0.013533339 | Q69: =1.25*MAX(Q45,0,'Correlation Matrix'!$B$44*SQRT('Covariance Matrix'!$Q$68*R69)) -> 0.015308728 | R69: =R45*1.25 -> 0.018230405 | S69: 0.063699295 | T69: 0.066966976 | U69: 0.06602353
A70: Oil Basket | B70: =1.25*MAX(B46,0,'Correlation Matrix'!$B$44*SQRT('Covariance Matrix'!$B$53*S70)) -> 0.09907247 | C70: =1.25*MAX(C46,0,'Correlation Matrix'!$B$44*SQRT('Covariance Matrix'!$C$54*S70)) -> 0.11011455 | D70: =1.25*MAX(D46,0,'Correlation Matrix'!$B$44*SQRT('Covariance Matrix'!$D$55*S70)) -> 0.12353828 | E70: =1.25*MAX(E46,0,'Correlation Matrix'!$B$44*SQRT('Covariance Matrix'!$E$56*S70)) -> 0.11829787 | F70: =1.25*MAX(F46,0,'Correlation Matrix'!$B$44*SQRT('Covariance Matrix'!$F$57*S70)) -> 0.11715421 | G70: =1.25*MAX(G46,0,'Correlation Matrix'!$B$44*SQRT('Covariance Matrix'!$G$58*S70)) -> 0.093196317 | H70: =1.25*MAX(H46,0,'Correlation Matrix'!$B$44*SQRT('Covariance Matrix'!$H$59*S70)) -> 0.12804086 | I70: =1.25*MAX(I46,0,'Correlation Matrix'!$B$44*SQRT('Covariance Matrix'!$I$60*S70)) -> 0.083489983 | J70: =1.25*MAX(J46,0,'Correlation Matrix'!$B$44*SQRT('Covariance Matrix'!$J$61*S70)) -> 0.097798518 | K70: =1.25*MAX(K46,0,'Correlation Matrix'!$B$44*SQRT('Covariance Matrix'!$K$62*S70)) -> 0.094018939 | L70: =1.25*MAX(L46,0,'Correlation Matrix'!$B$44*SQRT('Covariance Matrix'!$L$63*S70)) -> 0.077524007 | M70: =1.25*MAX(M46,0,'Correlation Matrix'!$B$44*SQRT('Covariance Matrix'!$M$64*S70)) -> 0.1032056 | N70: =1.25*MAX(N46,0,'Correlation Matrix'!$B$44*SQRT('Covariance Matrix'!$N$65*S70)) -> 0.098310915 | O70: =1.25*MAX(O46,0,'Correlation Matrix'!$B$44*SQRT('Covariance Matrix'!$O$66*S70)) -> 0.019828894 | P70: =1.25*MAX(P46,0,'Correlation Matrix'!$B$44*SQRT('Covariance Matrix'!$P$67*S70)) -> 0.043026531 | Q70: =1.25*MAX(Q46,0,'Correlation Matrix'!$B$44*SQRT('Covariance Matrix'!$Q$68*S70)) -> 0.048671022 | R70: =1.25*MAX(R46,0,'Correlation Matrix'!$B$44*SQRT('Covariance Matrix'!$R$69*S70)) -> 0.063699295 | S70: =S46*1.25 -> 0.18427187 | T70: 0.21290804 | U70: 0.20990854
A71: Timber Basket | B71: =1.25*MAX(B47,0,'Correlation Matrix'!$B$44*SQRT('Covariance Matrix'!$B$53*T71)) -> 0.10415474 | C71: =1.25*MAX(C47,0,'Correlation Matrix'!$B$44*SQRT('Covariance Matrix'!$C$54*T71)) -> 0.11576327 | D71: =1.25*MAX(D47,0,'Correlation Matrix'!$B$44*SQRT('Covariance Matrix'!$D$55*T71)) -> 0.12987561 | E71: =1.25*MAX(E47,0,'Correlation Matrix'!$B$44*SQRT('Covariance Matrix'!$E$56*T71)) -> 0.12436638 | F71: =1.25*MAX(F47,0,'Correlation Matrix'!$B$44*SQRT('Covariance Matrix'!$F$57*T71)) -> 0.12316405 | G71: =1.25*MAX(G47,0,'Correlation Matrix'!$B$44*SQRT('Covariance Matrix'!$G$58*T71)) -> 0.097977153 | H71: =1.25*MAX(H47,0,'Correlation Matrix'!$B$44*SQRT('Covariance Matrix'!$H$59*T71)) -> 0.13460917 | I71: =1.25*MAX(I47,0,'Correlation Matrix'!$B$44*SQRT('Covariance Matrix'!$I$60*T71)) -> 0.087772898 | J71: =1.25*MAX(J47,0,'Correlation Matrix'!$B$44*SQRT('Covariance Matrix'!$J$61*T71)) -> 0.10281544 | K71: =1.25*MAX(K47,0,'Correlation Matrix'!$B$44*SQRT('Covariance Matrix'!$K$62*T71)) -> 0.098841975 | L71: =1.25*MAX(L47,0,'Correlation Matrix'!$B$44*SQRT('Covariance Matrix'!$L$63*T71)) -> 0.081500876 | M71: =1.25*MAX(M47,0,'Correlation Matrix'!$B$44*SQRT('Covariance Matrix'!$M$64*T71)) -> 0.1084999 | N71: =1.25*MAX(N47,0,'Correlation Matrix'!$B$44*SQRT('Covariance Matrix'!$N$65*T71)) -> 0.10335412 | O71: =1.25*MAX(O47,0,'Correlation Matrix'!$B$44*SQRT('Covariance Matrix'!$O$66*T71)) -> 0.020846087 | P71: =1.25*MAX(P47,0,'Correlation Matrix'!$B$44*SQRT('Covariance Matrix'!$P$67*T71)) -> 0.045233729 | Q71: =1.25*MAX(Q47,0,'Correlation Matrix'!$B$44*SQRT('Covariance Matrix'!$Q$68*T71)) -> 0.051167775 | R71: =1.25*MAX(R47,0,'Correlation Matrix'!$B$44*SQRT('Covariance Matrix'!$R$69*T71)) -> 0.066966976 | S71: =1.25*MAX(S47,0,'Correlation Matrix'!$B$44*SQRT('Covariance Matrix'!$S$70*T71)) -> 0.21290804 | T71: =T47*1.25 -> 0.20366255 | U71: 0.22067654
A72: STOR | B72: =1.25*MAX(B48,0,'Correlation Matrix'!$B$44*SQRT('Covariance Matrix'!$B$53*U72)) -> 0.10268739 | C72: =1.25*MAX(C48,0,'Correlation Matrix'!$B$44*SQRT('Covariance Matrix'!$C$54*U72)) -> 0.11413237 | D72: =1.25*MAX(D48,0,'Correlation Matrix'!$B$44*SQRT('Covariance Matrix'!$D$55*U72)) -> 0.12804589 | E72: =1.25*MAX(E48,0,'Correlation Matrix'!$B$44*SQRT('Covariance Matrix'!$E$56*U72)) -> 0.12261427 | F72: =1.25*MAX(F48,0,'Correlation Matrix'!$B$44*SQRT('Covariance Matrix'!$F$57*U72)) -> 0.12142889 | G72: =1.25*MAX(G48,0,'Correlation Matrix'!$B$44*SQRT('Covariance Matrix'!$G$58*U72)) -> 0.096596829 | H72: =1.25*MAX(H48,0,'Correlation Matrix'!$B$44*SQRT('Covariance Matrix'!$H$59*U72)) -> 0.13271276 | I72: =1.25*MAX(I48,0,'Correlation Matrix'!$B$44*SQRT('Covariance Matrix'!$I$60*U72)) -> 0.086536333 | J72: =1.25*MAX(J48,0,'Correlation Matrix'!$B$44*SQRT('Covariance Matrix'!$J$61*U72)) -> 0.10136695 | K72: =1.25*MAX(K48,0,'Correlation Matrix'!$B$44*SQRT('Covariance Matrix'!$K$62*U72)) -> 0.097449466 | L72: =1.25*MAX(L48,0,'Correlation Matrix'!$B$44*SQRT('Covariance Matrix'!$L$63*U72)) -> 0.080352673 | M72: =1.25*MAX(M48,0,'Correlation Matrix'!$B$44*SQRT('Covariance Matrix'!$M$64*U72)) -> 0.10697133 | N72: =1.25*MAX(N48,0,'Correlation Matrix'!$B$44*SQRT('Covariance Matrix'!$N$65*U72)) -> 0.10189805 | O72: =1.25*MAX(O48,0,'Correlation Matrix'!$B$44*SQRT('Covariance Matrix'!$O$66*U72)) -> 0.020552403 | P72: =1.25*MAX(P48,0,'Correlation Matrix'!$B$44*SQRT('Covariance Matrix'!$P$67*U72)) -> 0.044596466 | Q72: =1.25*MAX(Q48,0,'Correlation Matrix'!$B$44*SQRT('Covariance Matrix'!$Q$68*U72)) -> 0.050446912 | R72: =1.25*MAX(R48,0,'Correlation Matrix'!$B$44*SQRT('Covariance Matrix'!$R$69*U72)) -> 0.06602353 | S72: =1.25*MAX(S48,0,'Correlation Matrix'!$B$44*SQRT('Covariance Matrix'!$S$70*U72)) -> 0.20990854 | T72: =1.25*MAX(T48,0,'Correlation Matrix'!$B$44*SQRT('Covariance Matrix'!$T$71*U72)) -> 0.22067654 | U72: =U48*1.25 -> 0.19796448
C74: Adusted Shrunked Matrix (15/85)
B76: VTI | C76: VO | D76: VB | E76: VWUSX | F76: VLUE | G76: VYM | H76: VCR | I76: VHT | J76: SCHF | K76: VWO | L76: EFG | M76: IVLU | N76: VYMI | O76: FBNDX | P76: VWEHX | Q76: PICB | R76: HYXU | S76: Oil Basket | T76: Timber Basket | U76: STOR
A77: VTI | B77: =(0.15*B29)+(0.85*B53) -> 0.042776454 | C77: =(0.15*C29)+(0.85*C53) -> 0.051537641 | D77: =(0.15*D29)+(0.85*D53) -> 0.057653796 | E77: =(0.15*E29)+(0.85*E53) -> 0.054870663 | F77: =(0.15*F29)+(0.85*F53) -> 0.054452778 | G77: =(0.15*G29)+(0.85*G53) -> 0.043470562 | H77: =(0.15*H29)+(0.85*H53) -> 0.059783579 | I77: =(0.15*I29)+(0.85*I53) -> 0.03848592 | ... U77: =(0.15*U29)+(0.85*U53) -> 0.095011434
A78: VO | B78: =(0.15*B30)+(0.85*B54) -> 0.051537641 | C78: =(0.15*C30)+(0.85*C54) -> 0.052843095 | D78: =(0.15*D30)+(0.85*D54) -> 0.064283608 | E78: =(0.15*E30)+(0.85*E54) -> 0.060677801 | F78: =(0.15*F30)+(0.85*F54) -> 0.060590877 | G78: =(0.15*G30)+(0.85*G54) -> 0.048311573 | H78: =(0.15*H30)+(0.85*H54) -> 0.066204103 | I78: =(0.15*I30)+(0.85*I54) -> 0.042594822 | ... U78: =(0.15*U30)+(0.85*U54) -> 0.10580155
A79: VB | B79: =(0.15*B31)+(0.85*B55) -> 0.057653796 | C79: =(0.15*C31)+(0.85*C55) -> 0.064283608 | D79: =(0.15*D31)+(0.85*D55) -> 0.066512287 | E79: =(0.15*E31)+(0.85*E55) -> 0.067851022 | F79: =(0.15*F31)+(0.85*F55) -> 0.068069742 | G79: =(0.15*G31)+(0.85*G55) -> 0.054080903 | H79: =(0.15*H31)+(0.85*H55) -> 0.074103484 | I79: =(0.15*I31)+(0.85*I55) -> 0.047595102 | ... U79: =(0.15*U31)+(0.85*U55) -> 0.11860847
A80: VWUSX | B80: =(0.15*B32)+(0.85*B56) -> 0.054870663 | C80: =(0.15*C32)+(0.85*C56) -> 0.060677801 | D80: =(0.15*D32)+(0.85*D56) -> 0.067851022 | E80: =(0.15*E32)+(0.85*E56) -> 0.060989158 | F80: =(0.15*F32)+(0.85*F56) -> 0.063582979 | G80: =(0.15*G32)+(0.85*G56) -> 0.050724985 | H80: =(0.15*H32)+(0.85*H56) -> 0.070970083 | I80: =(0.15*I32)+(0.85*I56) -> 0.045387241 | ... U80: =(0.15*U32)+(0.85*U56) -> 0.11229038
A81: VLUE | B81: =(0.15*B33)+(0.85*B57) -> 0.054452778 | C81: =(0.15*C33)+(0.85*C57) -> 0.060590877 | D81: =(0.15*D33)+(0.85*D57) -> 0.068069742 | E81: =(0.15*E33)+(0.85*E57) -> 0.063582979 | F81: =(0.15*F33)+(0.85*F57) -> 0.059815619 | G81: =(0.15*G33)+(0.85*G57) -> 0.051481444 | H81: =(0.15*H33)+(0.85*H57) -> 0.069761575 | I81: =(0.15*I33)+(0.85*I57) -> 0.044955402 | ... U81: =(0.15*U33)+(0.85*U57) -> 0.11162174
A82: VYM | B82: =(0.15*B34)+(0.85*B58) -> 0.043470562 | C82: =(0.15*C34)+(0.85*C58) -> 0.048311573 | D82: =(0.15*D34)+(0.85*D58) -> 0.054080903 | E82: =(0.15*E34)+(0.85*E58) -> 0.050724985 | F82: =(0.15*F34)+(0.85*F58) -> 0.051481444 | G82: =(0.15*G34)+(0.85*G58) -> 0.037852652 | H82: =(0.15*H34)+(0.85*H58) -> 0.055642775 | I82: =(0.15*I34)+(0.85*I58) -> 0.036011772 | ... U82: =(0.15*U34)+(0.85*U58) -> 0.088849235
A83: VCR | B83: =(0.15*B35)+(0.85*B59) -> 0.059783579 | C83: =(0.15*C35)+(0.85*C59) -> 0.066204103 | D83: =(0.15*D35)+(0.85*D59) -> 0.074103484 | E83: =(0.15*E35)+(0.85*E59) -> 0.070970083 | F83: =(0.15*F35)+(0.85*F59) -> 0.069761575 | G83: =(0.15*G35)+(0.85*G59) -> 0.055642775 | H83: =(0.15*H35)+(0.85*H59) -> 0.071448968 | I83: =(0.15*I35)+(0.85*I59) -> 0.049466427 | ... U83: =(0.15*U35)+(0.85*U59) -> 0.12267241
A84: VHT | B84: =(0.15*B36)+(0.85*B60) -> 0.03848592 | C84: =(0.15*C36)+(0.85*C60) -> 0.042594822 | D84: =(0.15*D36)+(0.85*D60) -> 0.047595102 | E84: =(0.15*E36)+(0.85*E60) -> 0.045387241 | F84: =(0.15*F36)+(0.85*F60) -> 0.044955402 | G84: =(0.15*G36)+(0.85*G60) -> 0.036011772 | H84: =(0.15*H36)+(0.85*H60) -> 0.049466427 | I84: =(0.15*I36)+(0.85*I60) -> 0.030378586 | ... U84: =(0.15*U36)+(0.85*U60) -> 0.077787709
A85: SCHF | B85: =(0.15*B37)+(0.85*B61) -> 0.045036928 | C85: =(0.15*C37)+(0.85*C61) -> 0.050050621 | D85: =(0.15*D37)+(0.85*D61) -> 0.056159173 | E85: =(0.15*E37)+(0.85*E61) -> 0.05294316 | F85: =(0.15*F37)+(0.85*F61) -> 0.053301026 | G85: =(0.15*G37)+(0.85*G61) -> 0.042395056 | H85: =(0.15*H37)+(0.85*H61) -> 0.05779349 | I85: =(0.15*I37)+(0.85*I61) -> 0.037205729 | ... U85: =(0.15*U37)+(0.85*U61) -> 0.093594639
A86: VWO | B86: =(0.15*B38)+(0.85*B62) -> 0.043129702 | C86: =(0.15*C38)+(0.85*C62) -> 0.048081382 | D86: =(0.15*D38)+(0.85*D62) -> 0.054135809 | E86: =(0.15*E38)+(0.85*E62) -> 0.050891511 | F86: =(0.15*F38)+(0.85*F62) -> 0.050946995 | G86: =(0.15*G38)+(0.85*G62) -> 0.040414212 | H86: =(0.15*H38)+(0.85*H62) -> 0.055712146 | I86: =(0.15*I38)+(0.85*I62) -> 0.035752058 | ... U86: =(0.15*U38)+(0.85*U62) -> 0.089421235
A87: EFG | B87: =(0.15*B39)+(0.85*B63) -> 0.036098101 | C87: =(0.15*C39)+(0.85*C63) -> 0.040052373 | D87: =(0.15*D39)+(0.85*D63) -> 0.044787245 | E87: =(0.15*E39)+(0.85*E63) -> 0.0426352 | F87: =(0.15*F39)+(0.85*F63) -> 0.042364535 | G87: =(0.15*G39)+(0.85*G63) -> 0.033820978 | H87: =(0.15*H39)+(0.85*H63) -> 0.046314673 | I87: =(0.15*I39)+(0.85*I63) -> 0.029958802 | ... U87: =(0.15*U39)+(0.85*U63) -> 0.074481263
A88: IVLU | B88: =(0.15*B40)+(0.85*B64) -> 0.047608832 | C88: =(0.15*C40)+(0.85*C64) -> 0.052933881 | D88: =(0.15*D40)+(0.85*D64) -> 0.059560799 | E88: =(0.15*E40)+(0.85*E64) -> 0.055556735 | F88: =(0.15*F40)+(0.85*F64) -> 0.056881485 | G88: =(0.15*G40)+(0.85*G64) -> 0.045064581 | H88: =(0.15*H40)+(0.85*H64) -> 0.060953822 | I88: =(0.15*I40)+(0.85*I64) -> 0.039141259 | ... U88: =(0.15*U40)+(0.85*U64) -> 0.099078332
... A96: STOR | B96: =(0.15*B48)+(0.85*B72) -> 0.095011434 | C96: =(0.15*C48)+(0.85*C72) -> 0.10580155 | D96: =(0.15*D48)+(0.85*D72) -> 0.11860847 | E96: =(0.15*E48)+(0.85*E72) -> 0.11229038 | F96: =(0.15*F48)+(0.85*F72) -> 0.11162174 | G96: =(0.15*G48)+(0.85*G72) -> 0.088849235 | H96: =(0.15*H48)+(0.85*H72) -> 0.12267241 | I96: =(0.15*I48)+(0.85*I72) -> 0.077787709 | ... U96: =(0.15*U48)+(0.85*U72) -> 0.19202555

Sheet Correlation Matrix
B1: VTI | C1: VO | D1: VB | E1: VWUSX | F1: VLUE | G1: VYM | H1: VCR | I1: VHT | J1: SCHF | K1: VWO | L1: EFG | M1: IVLU | N1: VYMI | O1: FBNDX | P1: VWEHX | Q1: PICB | R1: HYXU | S1: Oil Basket | T1: Timber Basket | U1: STOR
A2: VTI | B2: 1
A3: VO | B3: 0.90234957 | C3: 1
A4: VB | B4: 0.90436193 | C4: 0.99861638 | D4: 1
A5: VWUSX | B5: 0.86490389 | C5: 0.96215678 | D5: 0.95059358 | E5: 1
A6: VLUE | B6: 0.8904867 | C6: 0.98529034 | D6: 0.99041247 | E6: 0.91208751 | F6: 1
A7: VYM | B7: 0.88963742 | C7: 0.98949599 | D7: 0.99199721 | E7: 0.92489003 | F7: 0.99819615 | G7: 1
A8: VCR | B8: 0.89455443 | C8: 0.98910852 | D8: 0.98278423 | E8: 0.98340089 | F8: 0.95529568 | G8: 0.96315438 | H8: 1
A9: VHT | B9: 0.85616576 | C9: 0.95823579 | D9: 0.9507024 | E9: 0.94880059 | F9: 0.93933716 | G9: 0.95235664 | H9: 0.96123338 | I9: 1
A10: SCHF | B10: 0.89821392 | C10: 0.98742194 | D10: 0.9895673 | E10: 0.93049656 | F10: 0.98575461 | G10: 0.98573952 | H10: 0.96538989 | I10: 0.91987323 | J10: 1
A11: VWO | B11: 0.89251193 | C11: 0.9698541 | D11: 0.97158827 | E11: 0.92940899 | F11: 0.9490576 | G11: 0.94709414 | H11: 0.97052715 | I11: 0.91779063 | J11: 0.96245719 | K11: 1
A12: EFG | B12: 0.89539419 | C12: 0.9885944 | D12: 0.98473503 | E12: 0.96321041 | F12: 0.96952644 | G12: 0.97496126 | H12: 0.98045141 | I12: 0.94076948 | J12: 0.99141002 | K12: 0.96215546 | L12: 1
A13: IVLU | B13: 0.87986787 | C13: 0.96679694 | D13: 0.97485783 | E13: 0.87863905 | F13: 0.98796101 | G13: 0.98331507 | H13: 0.92738591 | I13: 0.88862191 | J13: 0.98911718 | K13: 0.93122382 | L13: 0.96328417 | M13: 1
A14: VYMI | B14: 0.89646902 | C14: 0.98130962 | D14: 0.98673742 | E14: 0.906992 | F14: 0.98685939 | G14: 0.98368316 | H14: 0.95437949 | I14: 0.90408577 | J14: 0.99658728 | K14: 0.96499831 | L14: 0.9787567 | M14: 0.99305698 | N14: 1
A15: FBNDX | B15: 0.46824184 | C15: 0.47575115 | D15: 0.45255053 | E15: 0.56850865 | F15: 0.34153998 | G15: 0.35692431 | H15: 0.55538849 | I15: 0.39179078 | J15: 0.45472352 | K15: 0.55083007 | L15: 0.50819411 | M15: 0.34898498 | N15: 0.43991866 | O15: 1
A16: VWEHX | B16: 0.88468375 | C16: 0.96514945 | D16: 0.96220113 | E16: 0.94082093 | F16: 0.92710614 | G16: 0.92796168 | H16: 0.97428572 | I16: 0.9016651 | J16: 0.95021205 | K16: 0.98725364 | L16: 0.95815849 | M16: 0.90783776 | N16: 0.94880618 | O16: 0.63703092 | P16: 1
A17: PICB | B17: 0.82979728 | C17: 0.89404705 | D17: 0.88535293 | E17: 0.89517537 | F17: 0.83150567 | G17: 0.83616249 | H17: 0.92496999 | I17: 0.82591267 | J17: 0.88488053 | K17: 0.94450668 | L17: 0.90597806 | M17: 0.82111149 | N17: 0.88066903 | O17: 0.77897898 | P17: 0.97085996 | Q17: 1
A18: HYXU | B18: 0.88307915 | C18: 0.95492352 | D18: 0.95297495 | E18: 0.9251561 | F18: 0.91932219 | G18: 0.91971435 | H18: 0.96529335 | I18: 0.88348244 | J18: 0.94990177 | K18: 0.98396875 | L18: 0.95361908 | M18: 0.91026362 | N18: 0.95160728 | O18: 0.65490797 | P18: 0.99298429 | Q18: 0.97938347 | R18: 1
A19: Oil Basket | B19: 0.8317137 | C19: 0.9168751 | D19: 0.92971352 | E19: 0.81013027 | F19: 0.95182164 | G19: 0.94781297 | H19: 0.87018626 | I19: 0.86066784 | J19: 0.91560457 | K19: 0.85743628 | L19: 0.87371261 | M19: 0.94955403 | N19: 0.93087685 | O19: 0.21999883 | P19: 0.82535266 | Q19: 0.70641686 | R19: 0.82863162 | S19: 1
A20: Timber Basket | B20: 0.86449957 | C20: 0.94116317 | D20: 0.93783595 | E20: 0.91499696 | F20: 0.90554097 | G20: 0.90708245 | H20: 0.96040825 | I20: 0.90435595 | J20: 0.91411768 | K20: 0.97734008 | L20: 0.92131049 | M20: 0.87167477 | N20: 0.91825671 | O20: 0.61941941 | P20: 0.98344096 | Q20: 0.96054031 | R20: 0.98219642 | S20: 0.81753558 | T20: 1
A21: STOR | B21: 0.78193408 | C21: 0.84999338 | D21: 0.84607518 | E21: 0.81670316 | F21: 0.80888267 | G21: 0.81224097 | H21: 0.84078539 | I21: 0.71045057 | J21: 0.88526352 | K21: 0.83258711 | L21: 0.8829024 | M21: 0.85654832 | N21: 0.87769814 | O21: 0.69390804 | P21: 0.86242318 | Q21: 0.87123079 | R21: 0.87550386 | S21: 0.73293808 | T21: 0.78870968 | U21: 1
B23: 0.90234957 | C23: 0.99861638 | D23: 0.95059358 | E23: 0.91208751 | F23: 0.99819615 | G23: 0.96315438 | H23: 0.96123338 | I23: 0.91987323 | J23: 0.96245719 | K23: 0.96215546 | L23: 0.96328417 | M23: 0.99305698 | N23: 0.43991866 | O23: 0.63703092 | P23: 0.97085996 | Q23: 0.97938347 | R23: 0.82863162 | S23: 0.81753558 | T23: 0.78870968
B24: 0.90436193 | C24: 0.96215678 | D24: 0.99041247 | E24: 0.92489003 | F24: 0.95529568 | G24: 0.95235664 | H24: 0.96538989 | I24: 0.91779063 | J24: 0.99141002 | K24: 0.93122382 | L24: 0.9787567 | M24: 0.34898498 | N24: 0.94880618 | O24: 0.77897898 | P24: 0.99298429 | Q24: 0.70641686 | R24: 0.98219642 | S24: 0.73293808
B25: 0.86490389 | C25: 0.98529034 | D25: 0.99199721 | E25: 0.98340089 | F25: 0.93933716 | G25: 0.98573952 | H25: 0.97052715 | I25: 0.94076948 | J25: 0.98911718 | K25: 0.96499831 | L25: 0.50819411 | M25: 0.90783776 | N25: 0.88066903 | O25: 0.65490797 | P25: 0.82535266 | Q25: 0.96054031 | R25: 0.87550386
B26: 0.8904867 | C26: 0.98949599 | D26: 0.98278423 | E26: 0.94880059 | F26: 0.98575461 | G26: 0.94709414 | H26: 0.98045141 | I26: 0.88862191 | J26: 0.99658728 | K26: 0.55083007 | L26: 0.95815849 | M26: 0.82111149 | N26: 0.95160728 | O26: 0.21999883 | P26: 0.98344096 | Q26: 0.87123079
B27: 0.88963742 | C27: 0.98910852 | D27: 0.9507024 | E27: 0.93049656 | F27: 0.9490576 | G27: 0.97496126 | H27: 0.92738591 | I27: 0.90408577 | J27: 0.45472352 | K27: 0.98725364 | L27: 0.90597806 | M27: 0.91026362 | N27: 0.93087685 | O27: 0.61941941 | P27: 0.86242318
B28: 0.89455443 | C28: 0.95823579 | D28: 0.9895673 | E28: 0.92940899 | F28: 0.96952644 | G28: 0.98331507 | H28: 0.95437949 | I28: 0.39179078 | J28: 0.95021205 | K28: 0.94450668 | L28: 0.95361908 | M28: 0.94955403 | N28: 0.91825671 | O28: 0.69390804
B29: 0.85616576 | C29: 0.98742194 | D29: 0.97158827 | E29: 0.96321041 | F29: 0.98796101 | G29: 0.98368316 | H29: 0.55538849 | I29: 0.9016651 | J29: 0.88488053 | K29: 0.98396875 | L29: 0.87371261 | M29: 0.87167477 | N29: 0.87769814
B30: 0.89821392 | C30: 0.9698541 | D30: 0.98473503 | E30: 0.87863905 | F30: 0.98685939 | G30: 0.35692431 | H30: 0.97428572 | I30: 0.82591267 | J30: 0.94990177 | K30: 0.85743628 | L30: 0.92131049 | M30: 0.85654832
B31: 0.89251193 | C31: 0.9885944 | D31: 0.97485783 | E31: 0.906992 | F31: 0.34153998 | G31: 0.92796168 | H31: 0.92496999 | I31: 0.88348244 | J31: 0.91560457 | K31: 0.97734008 | L31: 0.8829024
B32: 0.89539419 | C32: 0.96679694 | D32: 0.98673742 | E32: 0.56850865 | F32: 0.92710614 | G32: 0.83616249 | H32: 0.96529335 | I32: 0.86066784 | J32: 0.91411768 | K32: 0.83258711
B33: 0.87986787 | C33: 0.98130962 | D33: 0.45255053 | E33: 0.94082093 | F33: 0.83150567 | G33: 0.91971435 | H33: 0.87018626 | I33: 0.90435595 | J33: 0.88526352
B34: 0.89646902 | C34: 0.47575115 | D34: 0.96220113 | E34: 0.89517537 | F34: 0.91932219 | G34: 0.94781297 | H34: 0.96040825 | I34: 0.71045057
B35: 0.46824184 | C35: 0.96514945 | D35: 0.88535293 | E35: 0.9251561 | F35: 0.95182164 | G35: 0.90708245 | H35: 0.84078539
B36: 0.88468375 | C36: 0.89404705 | D36: 0.95297495 | E36: 0.81013027 | F36: 0.90554097 | G36: 0.81224097
B37: 0.82979728 | C37: 0.95492352 | D37: 0.92971352 | E37: 0.91499696 | F37: 0.80888267
B38: 0.88307915 | C38: 0.9168751 | D38: 0.93783595 | E38: 0.81670316
B39: 0.8317137 | C39: 0.94116317 | D39: 0.84607518
B40: 0.86449957 | C40: 0.84999338
B41: 0.78193408
A43: Average
A44: Correlation: | B44: =AVERAGE(B23:T41) -> 0.87921872

Sheet Solver
A1: Ticker | B1: VTI | C1: VO | D1: VB | E1: VWUSX | F1: VLUE | G1: VYM | H1: VCR | I1: VHT | J1: SCHF | K1: VWO | L1: EFG | M1: IVLU | N1: VYMI | O1: FBNDX | P1: VWEHX | Q1: PICB | R1: HYXU | S1: Oil Basket | T1: Timber Basket | U1: STOR | W1: GSPC
A2: Returns | B2: 0.020135642 | C2: 0.023392872 | D2: 0.021898284 | E2: 0.02666322 | F2: -0.0059279467 | G2: 0.035551053 | H2: 0.023273062 | I2: 0.065273197 | J2: 0.0052099208 | K2: 0.048335784 | L2: 0.0074349554 | M2: -0.0033727917 | N2: 0.0088539492 | O2: 0.0052842108 | P2: -0.0070507259 | Q2: -0.012940664 | R2: -0.017561315 | S2: 0.010113431 | T2: -0.017080732 | U2: 0.032035467 | W2: 0.017859382
B3: -0.091761055 | C3: -0.098025633 | D3: -0.11112112 | E3: -0.09085557 | F3: -0.11052319 | G3: -0.086647546 | H3: -0.088754558 | I3: -0.091387839 | J3: -0.054022923 | K3: -0.033449906 | L3: -0.050489939 | M3: -0.062857088 | N3: -0.041566704 | O3: 0.015302994 | P3: -0.021294341 | Q3: 0.013770781 | R3: 0.0092931443 | S3: -0.095157768 | T3: -0.082211878 | U3: -0.044112867 | W3: -0.091776956
B4: 0.085402381 | C4: 0.10471827 | D4: 0.11712965 | E4: 0.094755476 | F4: 0.098387498 | G4: 0.061033574 | H4: 0.10085122 | I4: 0.059340365 | J4: 0.07195753 | K4: 0.096587827 | L4: 0.061676722 | M4: 0.080475472 | N4: 0.070375171 | O4: 0.015530912 | P4: 0.049409077 | Q4: 0.02918282 | R4: 0.023395434 | S4: 0.071385125 | T4: 0.14658667 | U4: 0.14164603 | W4: 0.078684405
B5: 0.035587945 | C5: 0.042581103 | D5: 0.048559231 | E5: 0.044093868 | F5: 0.01894367 | G5: 0.037703857 | H5: 0.015026781 | I5: 0.016398978 | J5: 0.024021045 | K5: -0.0038296917 | L5: 0.033410483 | M5: 0.0059243427 | N5: 0.015606851 | O5: 0.0010351346 | P5: 0.01501068 | Q5: 0.006008248 | R5: 0.012340873 | S5: 0.05027969 | T5: -0.041103701 | U5: 0.0046414171 | W5: 0.02972893
B6: 0.014167673 | C6: 0.013529287 | D6: -0.0085803286 | E6: 0.016683683 | F6: -0.0095208703 | G6: 0.0052353703 | H6: 0.027674923 | I6: 0.0038264212 | J6: 0.0061055866 | K6: 0.023148306 | L6: 0.022037338 | M6: -0.00075698964 | N6: 0.0021617997 | O6: 0.019336132 | P6: 0.0099693849 | Q6: 0.0078449642 | R6: -0.0039967891 | S6: 0.012047566 | T6: 0.0016050625 | U6: 0.041976313 | W6: 0.017924288
B7: 0.03925079 | C7: 0.037137855 | D7: 0.035863903 | E7: 0.14328428 | F7: 0.034184583 | G7: 0.028367844 | H7: 0.051041047 | I7: -0.026959034 | J7: 0.028744583 | K7: 0.021411964 | L7: 0.034990614 | M7: 0.01717745 | N7: 0.02842596 | O7: 0.0024170414 | P7: 0.014951046 | Q7: -0.00022520302 | R7: 0.012038483 | S7: -0.028668156 | T7: 0.039923455 | U7: -0.0053730284 | W7: 0.039313435
B8: -0.064498857 | C8: -0.060580456 | D8: -0.071771422 | E8: -0.060694927 | F8: -0.096016368 | G8: -0.063117328 | H8: -0.078969371 | I8: -0.026753652 | J8: -0.052157622 | K8: -0.063810271 | L8: -0.042040943 | M8: -0.073675848 | N8: -0.053363198 | O8: 0.015097145 | P8: -0.010827392 | Q8: -0.010945912 | R8: -0.019230848 | S8: -0.070668176 | T8: -0.1596295 | U8: 0.027010607 | W8: -0.065777726
B9: 0.070780583 | C9: 0.071010117 | D9: 0.069689174 | E9: 0.073475491 | F9: 0.095697945 | G9: 0.066443621 | H9: 0.077568828 | I9: 0.071989839 | J9: 0.059591161 | K9: 0.053718492 | L9: 0.064857947 | M9: 0.052624997 | N9: 0.053720491 | O9: 0.014776506 | P9: 0.027245509 | Q9: 0.033051183 | R9: 0.039417804 | S9: 0.070140348 | T9: 0.1520627 | U9: -0.020317144 | W9: 0.068930183
B10: 0.01412512 | C10: 0.013101356 | D10: 0.012000213 | E10: 0.012621592 | F10: 0.016011972 | G10: 0.0072099112 | H10: 0.011595048 | I10: -0.01305031 | J10: -0.019632322 | K10: -0.018104649 | L10: -0.011390358 | M10: -0.020824068 | N10: -0.02688181 | O10: 0.0023571247 | P10: 0.0044564918 | Q10: -0.013418341 | R10: -0.019642119 | S10: -0.022288071 | T10: -0.072549338 | U10: 0.030732144 | W10: 0.013128195
B11: -0.02082677 | C11: -0.027576177 | D11: -0.039674585 | E11: -0.01677858 | F11: -0.045217683 | G11: -0.021020431 | H11: -0.017358461 | I11: -0.011767143 | J11: -0.018753707 | K11: -0.03256711 | L11: -0.0055103326 | M11: -0.035445042 | N11: -0.034488336 | O11: 0.023245905 | P11: 0.0095835561 | Q11: 0.0088005908 | R11: 0.00039678611 | S11: -0.07278911 | T11: 0.045102442 | U11: 0.10377091 | W11: -0.018091653
B12: 0.017792804 | C12: 0.020970813 | D12: 0.013667671 | E12: -0.012189369 | F12: 0.048549396 | G12: 0.038954588 | H12: 0.013397385 | I12: -0.0079013048 | J12: 0.032069733 | K12: 0.0091090802 | L12: 0.013852226 | M12: 0.046853177 | N12: 0.041206644 | O12: -0.0038665768 | P12: 0.0042625336 | Q12: -0.0079514433 | R12: -0.0093199609 | S12: 0.043523102 | T12: 0.062331578 | U12: -6.1660721e-05 | W12: 0.017181168
B13: 0.021060071 | C13: 0.011098215 | D13: 0.016504843 | E13: 0.025419733 | F13: 0.028400774 | G13: 0.010481276 | H13: 0.0071065245 | I13: 0.047829499 | J13: 0.031387585 | K13: 0.039493334 | L13: 0.032666691 | M13: 0.039052051 | N13: 0.033002221 | O13: 0.0045210737 | P13: 0.0061315844 | Q13: 0.025883421 | R13: 0.023418804 | S13: -0.029235912 | T13: 0.10053296 | U13: 0.082598301 | W13: 0.020431747
B14: 0.037877539 | C14: 0.032219718 | D14: 0.041999844 | E14: 0.05126351 | F14: 0.03697992 | G14: 0.023421918 | H14: 0.018632982 | I14: 0.061297777 | J14: 0.012477044 | K14: 0.0050178266 | L14: 0.018041809 | M14: 0.013175886 | N14: 0.0073350213 | O14: -0.00036003731 | P14: 0.0059503643 | Q14: -0.0077801686 | R14: -0.00097779586 | S14: 0.041592632 | T14: 0.031100432 | U14: 0.005184972 | W14: 0.034047064
... B37: 0.066873818 | C37: 0.065889508 | D37: 0.049480953 | E37: 0.072737368 | F37: 0.024826216 | G37: 0.049250121 | H37: 0.093041262 | I37: 0.045678912 | J37: 0.03255814 | K37: 0.012997401 | L37: 0.042077581 | M37: 0.012057565 | N37: 0.029674489 | O37: -0.0011904762 | P37: -0.0066889632 | Q37: 0.0060383631 | R37: -0.0050881337 | S37: 0.11011797 | T37: 0.079032944 | U37: 0.07180768 | W37: 0.069143873
A38: Beta | B38: =SLOPE(B2:B37,W2:W37) -> 1.0290576 | C38: =SLOPE(C$2:C$37,$W$2:$W$37) -> 1.1063456 | D38: =SLOPE(D$2:D$37,$W$2:$W$37) -> 1.1927321 | E38: =SLOPE(E$2:E$37,$W$2:$W$37) -> 1.1027866 | F38: =SLOPE(F$2:F$37,$W$2:$W$37) -> 1.1038458 | G38: =SLOPE(G$2:G$37,$W$2:$W$37) -> 0.91877651 | H38: =SLOPE(H$2:H$37,$W$2:$W$37) -> 1.2682613 | I38: =SLOPE(I$2:I$37,$W$2:$W$37) -> 0.73932412 | J38: =SLOPE(J$2:J$37,$W$2:$W$37) -> 0.84071189 | ... U38: =SLOPE(U$2:U$37,$W$2:$W$37) -> 1.4737245
A39: Expected return | B39: =0.02+B38*(0.075-0.02) -> 0.07659817 | C39: =0.02+C38*(0.075-0.02) -> 0.08084901 | D39: =0.02+D38*(0.075-0.02) -> 0.085600267 | E39: =0.02+E38*(0.075-0.02) -> 0.080653261 | F39: =0.02+F38*(0.075-0.02) -> 0.08071152 | G39: =0.02+G38*(0.075-0.02) -> 0.070532708 | H39: =0.02+H38*(0.075-0.02) -> 0.089754373 | I39: =0.02+I38*(0.075-0.02) -> 0.060662826 | ... U39: =0.02+U38*(0.075-0.02) -> 0.10105485
B41: Fund | C41: VTI | D41: VO | E41: VB | F41: VWUSX | G41: VLUE | H41: VYM | I41: VCR | J41: VHT | K41: SCHF | L41: VWO | M41: EFG | N41: IVLU | O41: VYMI | P41: FBNDX | Q41: VWEHX | R41: PICB | S41: HYXU | T41: Oil Basket | U41: Timber Basket | V41: STOR
B42: Weights | C42: 0.25057023 | D42: 0.069081257 | E42: 0.065427663 | F42: 0.10305341 | G42: 0.058321967 | H42: 0.0335527 | I42: 0.11999277 | J42: 0 | K42: 0.037570119 | L42: 0 | M42: 0.022714383 | N42: 0.025294082 | O42: 0.014421416 | P42: 0 | Q42: 0 | R42: 0 | S42: 0 | T42: 0.076130387 | U42: 0.088962668 | V42: 0.034906945
B43: Working | C43: {=MMULT($C$42:$V$42,'Covariance Matrix'!B29:B48)} -> 0.040878094 | D43: {=MMULT($C$42:$V$42,'Covariance Matrix'!C29:C48)} -> 0.04530472 | E43: {=MMULT($C$42:$V$42,'Covariance Matrix'!D29:D48)} -> 0.050382376 | F43: {=MMULT($C$42:$V$42,'Covariance Matrix'!E29:E48)} -> 0.043440581 | G43: {=MMULT($C$42:$V$42,'Covariance Matrix'!F29:F48)} -> 0.045828806 | H43: {=MMULT($C$42:$V$42,'Covariance Matrix'!G29:G48)} -> 0.036833518 | I43: {=MMULT($C$42:$V$42,'Covariance Matrix'!H29:H48)} -> 0.051655963 | J43: {=MMULT($C$42:$V$42,'Covariance Matrix'!I29:I48)} -> 0.028027207 | ... V43: {=MMULT($C$42:$V$42,'Covariance Matrix'!U29:U48)} -> 0.064930426
B44: Class Weight | C44: =SUM(C42:J42) -> 0.7 | K44: =SUM(K42:O42) -> 0.1 | P44: =SUM(P42:S42) -> 0 | T44: =SUM(T42:V42) -> 0.2
B47: Sum Weight | C47: =SUM(C42:V42) -> 1 | G47: Risk | H47: Return | I47: Min(risk) | J47: Min(return) | R47: VTI | S47: =C42 -> 0.25057023
B48: Risk(variance) | C48: {=MMULT(C43:V43,S47:S66)} -> 0.049193556 | D48: Risk (St.dev) | E48: =SQRT(C48) -> 0.2217962 | G48: 0.1048344 | H48: 0.049474959 | I48: 0.1048344 | J48: 0.049474959 | R48: VO | S48: =D42 -> 0.069081257
G49: 0.11997431 | H49: 0.055 | R49: VB | S49: =E42 -> 0.065427663
B50: Return | G50: 0.13509377 | H50: 0.06 | R50: VWUSX | S50: =F42 -> 0.10305341
B51: Actual | C51: =SUMPRODUCT(C42:V42,B39:U39) -> 0.085 | G51: 0.1496807 | H51: 0.065 | R51: VLUE | S51: =G42 -> 0.058321967
B52: Desired (Target) | C52: 0.085 | G52: 0.16610478 | H52: 0.07 | R52: VYM | S52: =H42 -> 0.0335527
G53: 0.18261296 | H53: 0.075 | R53: VCR | S53: =I42 -> 0.11999277
B54: Class Constraints | C54: MIN | D54: Weights | E54: MAX | G54: 0.20059708 | H54: 0.08 | R54: VHT | S54: =J42 -> 0
B55: Class A | C55: 0.3 | D55: to | E55: 0.95 | G55: 0.2217962 | H55: 0.085 | R55: SCHF | S55: =K42 -> 0.037570119
B56: Class B | C56: 0.1 | D56: to | E56: 0.4 | G56: 0.25756701 | H56: 0.093207564 | I56: Max | R56: VWO | S56: =L42 -> 0
B57: Class C | C57: 0 | D57: to | E57: 0.7 | R57: EFG | S57: =M42 -> 0.022714383
B58: Class D | C58: 0 | D58: to | E58: 0.2 | R58: IVLU | S58: =N42 -> 0.025294082
N59: ` | R59: VYMI | S59: =O42 -> 0.014421416
R60: FBNDX | S60: =P42 -> 0
R61: VWEHX | S61: =Q42 -> 0
R62: PICB | S62: =R42 -> 0
R63: HYXU | S63: =S42 -> 0
R64: Oil Basket | S64: =T42 -> 0.076130387
R65: Timber Basket | S65: =U42 -> 0.088962668
R66: STOR | S66: =V42 -> 0.034906945

Sheet Shrunken Solver
A1: Ticker | B1: VTI | C1: VO | D1: VB | E1: VWUSX | F1: VLUE | G1: VYM | H1: VCR | I1: VHT | J1: SCHF | K1: VWO | L1: EFG | M1: IVLU | N1: VYMI | O1: FBNDX | P1: VWEHX | Q1: PICB | R1: HYXU | S1: Oil Basket | T1: Timber Basket | U1: STOR | W1: GSPC
A2: Returns | B2: 0.020135642 | C2: 0.023392872 | D2: 0.021898284 | E2: 0.02666322 | F2: -0.0059279467 | G2: 0.035551053 | H2: 0.023273062 | I2: 0.065273197 | J2: 0.0052099208 | K2: 0.048335784 | L2: 0.0074349554 | M2: -0.0033727917 | N2: 0.0088539492 | O2: 0.0052842108 | P2: -0.0070507259 | Q2: -0.012940664 | R2: -0.017561315 | S2: 0.010113431 | T2: -0.017080732 | U2: 0.032035467 | W2: 0.017859382
B3: -0.091761055 | C3: -0.098025633 | D3: -0.11112112 | E3: -0.09085557 | F3: -0.11052319 | G3: -0.086647546 | H3: -0.088754558 | I3: -0.091387839 | J3: -0.054022923 | K3: -0.033449906 | L3: -0.050489939 | M3: -0.062857088 | N3: -0.041566704 | O3: 0.015302994 | P3: -0.021294341 | Q3: 0.013770781 | R3: 0.0092931443 | S3: -0.095157768 | T3: -0.082211878 | U3: -0.044112867 | W3: -0.091776956
B4: 0.085402381 | C4: 0.10471827 | D4: 0.11712965 | E4: 0.094755476 | F4: 0.098387498 | G4: 0.061033574 | H4: 0.10085122 | I4: 0.059340365 | J4: 0.07195753 | K4: 0.096587827 | L4: 0.061676722 | M4: 0.080475472 | N4: 0.070375171 | O4: 0.015530912 | P4: 0.049409077 | Q4: 0.02918282 | R4: 0.023395434 | S4: 0.071385125 | T4: 0.14658667 | U4: 0.14164603 | W4: 0.078684405
B5: 0.035587945 | C5: 0.042581103 | D5: 0.048559231 | E5: 0.044093868 | F5: 0.01894367 | G5: 0.037703857 | H5: 0.015026781 | I5: 0.016398978 | J5: 0.024021045 | K5: -0.0038296917 | L5: 0.033410483 | M5: 0.0059243427 | N5: 0.015606851 | O5: 0.0010351346 | P5: 0.01501068 | Q5: 0.006008248 | R5: 0.012340873 | S5: 0.05027969 | T5: -0.041103701 | U5: 0.0046414171 | W5: 0.02972893
B6: 0.014167673 | C6: 0.013529287 | D6: -0.0085803286 | E6: 0.016683683 | F6: -0.0095208703 | G6: 0.0052353703 | H6: 0.027674923 | I6: 0.0038264212 | J6: 0.0061055866 | K6: 0.023148306 | L6: 0.022037338 | M6: -0.00075698964 | N6: 0.0021617997 | O6: 0.019336132 | P6: 0.0099693849 | Q6: 0.0078449642 | R6: -0.0039967891 | S6: 0.012047566 | T6: 0.0016050625 | U6: 0.041976313 | W6: 0.017924288
B7: 0.03925079 | C7: 0.037137855 | D7: 0.035863903 | E7: 0.14328428 | F7: 0.034184583 | G7: 0.028367844 | H7: 0.051041047 | I7: -0.026959034 | J7: 0.028744583 | K7: 0.021411964 | L7: 0.034990614 | M7: 0.01717745 | N7: 0.02842596 | O7: 0.0024170414 | P7: 0.014951046 | Q7: -0.00022520302 | R7: 0.012038483 | S7: -0.028668156 | T7: 0.039923455 | U7: -0.0053730284 | W7: 0.039313435
B8: -0.064498857 | C8: -0.060580456 | D8: -0.071771422 | E8: -0.060694927 | F8: -0.096016368 | G8: -0.063117328 | H8: -0.078969371 | I8: -0.026753652 | J8: -0.052157622 | K8: -0.063810271 | L8: -0.042040943 | M8: -0.073675848 | N8: -0.053363198 | O8: 0.015097145 | P8: -0.010827392 | Q8: -0.010945912 | R8: -0.019230848 | S8: -0.070668176 | T8: -0.1596295 | U8: 0.027010607 | W8: -0.065777726
B9: 0.070780583 | C9: 0.071010117 | D9: 0.069689174 | E9: 0.073475491 | F9: 0.095697945 | G9: 0.066443621 | H9: 0.077568828 | I9: 0.071989839 | J9: 0.059591161 | K9: 0.053718492 | L9: 0.064857947 | M9: 0.052624997 | N9: 0.053720491 | O9: 0.014776506 | P9: 0.027245509 | Q9: 0.033051183 | R9: 0.039417804 | S9: 0.070140348 | T9: 0.1520627 | U9: -0.020317144 | W9: 0.068930183
B10: 0.01412512 | C10: 0.013101356 | D10: 0.012000213 | E10: 0.012621592 | F10: 0.016011972 | G10: 0.0072099112 | H10: 0.011595048 | I10: -0.01305031 | J10: -0.019632322 | K10: -0.018104649 | L10: -0.011390358 | M10: -0.020824068 | N10: -0.02688181 | O10: 0.0023571247 | P10: 0.0044564918 | Q10: -0.013418341 | R10: -0.019642119 | S10: -0.022288071 | T10: -0.072549338 | U10: 0.030732144 | W10: 0.013128195
B11: -0.02082677 | C11: -0.027576177 | D11: -0.039674585 | E11: -0.01677858 | F11: -0.045217683 | G11: -0.021020431 | H11: -0.017358461 | I11: -0.011767143 | J11: -0.018753707 | K11: -0.03256711 | L11: -0.0055103326 | M11: -0.035445042 | N11: -0.034488336 | O11: 0.023245905 | P11: 0.0095835561 | Q11: 0.0088005908 | R11: 0.00039678611 | S11: -0.07278911 | T11: 0.045102442 | U11: 0.10377091 | W11: -0.018091653
B12: 0.017792804 | C12: 0.020970813 | D12: 0.013667671 | E12: -0.012189369 | F12: 0.048549396 | G12: 0.038954588 | H12: 0.013397385 | I12: -0.0079013048 | J12: 0.032069733 | K12: 0.0091090802 | L12: 0.013852226 | M12: 0.046853177 | N12: 0.041206644 | O12: -0.0038665768 | P12: 0.0042625336 | Q12: -0.0079514433 | R12: -0.0093199609 | S12: 0.043523102 | T12: 0.062331578 | U12: -6.1660721e-05 | W12: 0.017181168
B13: 0.021060071 | C13: 0.011098215 | D13: 0.016504843 | E13: 0.025419733 | F13: 0.028400774 | G13: 0.010481276 | H13: 0.0071065245 | I13: 0.047829499 | J13: 0.031387585 | K13: 0.039493334 | L13: 0.032666691 | M13: 0.039052051 | N13: 0.033002221 | O13: 0.0045210737 | P13: 0.0061315844 | Q13: 0.025883421 | R13: 0.023418804 | S13: -0.029235912 | T13: 0.10053296 | U13: 0.082598301 | W13: 0.020431747
B14: 0.037877539 | C14: 0.032219718 | D14: 0.041999844 | E14: 0.05126351 | F14: 0.03697992 | G14: 0.023421918 | H14: 0.018632982 | I14: 0.061297777 | J14: 0.012477044 | K14: 0.0050178266 | L14: 0.018041809 | M14: 0.013175886 | N14: 0.0073350213 | O14: -0.00036003731 | P14: 0.0059503643 | Q14: -0.0077801686 | R14: -0.00097779586 | S14: 0.041592632 | T14: 0.031100432 | U14: 0.005184972 | W14: 0.034047064
... B37: 0.066873818 | C37: 0.065889508 | D37: 0.049480953 | E37: 0.072737368 | F37: 0.024826216 | G37: 0.049250121 | H37: 0.093041262 | I37: 0.045678912 | J37: 0.03255814 | K37: 0.012997401 | L37: 0.042077581 | M37: 0.012057565 | N37: 0.029674489 | O37: -0.0011904762 | P37: -0.0066889632 | Q37: 0.0060383631 | R37: -0.0050881337 | S37: 0.11011797 | T37: 0.079032944 | U37: 0.07180768 | W37: 0.069143873
A38: Beta | B38: =SLOPE(B2:B37,W2:W37) -> 1.0290576 | C38: =SLOPE(C$2:C$37,$W$2:$W$37) -> 1.1063456 | D38: =SLOPE(D$2:D$37,$W$2:$W$37) -> 1.1927321 | E38: =SLOPE(E$2:E$37,$W$2:$W$37) -> 1.1027866 | F38: =SLOPE(F$2:F$37,$W$2:$W$37) -> 1.1038458 | G38: =SLOPE(G$2:G$37,$W$2:$W$37) -> 0.91877651 | H38: =SLOPE(H$2:H$37,$W$2:$W$37) -> 1.2682613 | I38: =SLOPE(I$2:I$37,$W$2:$W$37) -> 0.73932412 | J38: =SLOPE(J$2:J$37,$W$2:$W$37) -> 0.84071189 | ... U38: =SLOPE(U$2:U$37,$W$2:$W$37) -> 1.4737245
A39: Expected return | B39: =0.02+B38*(0.075-0.02) -> 0.07659817 | C39: =0.02+C38*(0.075-0.02) -> 0.08084901 | D39: =0.02+D38*(0.075-0.02) -> 0.085600267 | E39: =0.02+E38*(0.075-0.02) -> 0.080653261 | F39: =0.02+F38*(0.075-0.02) -> 0.08071152 | G39: =0.02+G38*(0.075-0.02) -> 0.070532708 | H39: =0.02+H38*(0.075-0.02) -> 0.089754373 | I39: =0.02+I38*(0.075-0.02) -> 0.060662826 | ... U39: =0.02+U38*(0.075-0.02) -> 0.10105485
B41: Fund | C41: VTI | D41: VO | E41: VB | F41: VWUSX | G41: VLUE | H41: VYM | I41: VCR | J41: VHT | K41: SCHF | L41: VWO | M41: EFG | N41: IVLU | O41: VYMI | P41: FBNDX | Q41: VWEHX | R41: PICB | S41: HYXU | T41: Oil Basket | U41: Timber Basket | V41: STOR
B42: Weights | C42: 0 | D42: 0 | E42: 0 | F42: 0 | G42: 0 | H42: 0 | I42: 0 | J42: 0.3 | K42: 0 | L42: 0 | M42: 0.4 | N42: 0 | O42: 0 | P42: 0.3 | Q42: 0 | R42: 0 | S42: 0 | T42: 0 | U42: 0 | V42: 0
B43: Working | C43: {=MMULT($C$42:$V$42,'Covariance Matrix'!B77:B96)} -> 0.028533253 | D43: {=MMULT($C$42:$V$42,'Covariance Matrix'!C77:C96)} -> 0.031645642 | E43: {=MMULT($C$42:$V$42,'Covariance Matrix'!D77:D96)} -> 0.035363869 | F43: {=MMULT($C$42:$V$42,'Covariance Matrix'!E77:E96)} -> 0.033757504 | G43: {=MMULT($C$42:$V$42,'Covariance Matrix'!F77:F96)} -> 0.033380134 | H43: {=MMULT($C$42:$V$42,'Covariance Matrix'!G77:G96)} -> 0.026685681 | I43: {=MMULT($C$42:$V$42,'Covariance Matrix'!H77:H96)} -> 0.036693329 | J43: {=MMULT($C$42:$V$42,'Covariance Matrix'!I77:I96)} -> 0.023249737 | ... V43: {=MMULT($C$42:$V$42,'Covariance Matrix'!U77:U96)} -> 0.05865464
B44: Class Weight | C44: =SUM(C42:J42) -> 0.3 | K44: =SUM(K42:O42) -> 0.4 | P44: =SUM(P42:S42) -> 0.3 | T44: =SUM(T42:V42) -> 0
B47: Sum Weight | C47: =SUM(C42:V42) -> 1 | G47: Risk | H47: Return | I47: Min(risk) | J47: Min(return) | R47: VTI | S47: =C42 -> 0
B48: Risk(variance) | C48: {=MMULT(C43:V43,S47:S66)} -> 0.017171153 | D48: Risk (St.dev) | E48: =SQRT(C48) -> 0.13103874 | G48: 0.13103874 | H48: 0.049467856 | I48: 0.13103874 | J48: 0.049467856 | R48: VO | S48: =D42 -> 0
G49: 0.14270322 | H49: 0.055 | R49: VB | S49: =E42 -> 0
B50: Return | G50: 0.15947944 | H50: 0.06 | R50: VWUSX | S50: =F42 -> 0
B51: Actual | C51: =SUMPRODUCT(C42:V42,B39:U39) -> 0.049467856 | G51: 0.1725572 | H51: 0.065 | R51: VLUE | S51: =G42 -> 0
B52: Desired (Target) | C52: 0 | G52: 0.18792806 | H52: 0.07 | R52: VYM | S52: =H42 -> 0
G53: 0.20555046 | H53: 0.075 | R53: VCR | S53: =I42 -> 0
B54: Class Constraints | C54: MIN | D54: Weights | E54: MAX | G54: 0.2300199 | H54: 0.08 | R54: VHT | S54: =J42 -> 0.3
B55: Class A | C55: 0.3 | D55: to | E55: 0.95 | G55: 0.27687775 | H55: 0.085 | R55: SCHF | S55: =K42 -> 0
B56: Class B | C56: 0.1 | D56: to | E56: 0.4 | G56: 0.30241049 | H56: 0.093207564 | I56: Max | R56: VWO | S56: =L42 -> 0
B57: Class C | C57: 0 | D57: to | E57: 0.7 | R57: EFG | S57: =M42 -> 0.4
B58: Class D | C58: 0 | D58: to | E58: 0.2 | R58: IVLU | S58: =N42 -> 0
N59: ` | R59: VYMI | S59: =O42 -> 0
R60: FBNDX | S60: =P42 -> 0.3
B61: Investor Portfolio's | R61: VWEHX | S61: =Q42 -> 0
B62: Conservative: | C62: 30%VHT, 40% EFG, 30% FBNDX, | R62: PICB | S62: =R42 -> 0
B63: Moderate: | C63: 80.63% VTI, 10%EFG, 9.37% FBNDX | R63: HYXU | S63: =S42 -> 0
B64: Aggressive: | C64: 70% VCR,10% IVLU, 20% Timber | R64: Oil Basket | S64: =T42 -> 0
R65: Timber Basket | S65: =U42 -> 0
R66: STOR | S66: =V42 -> 0

Sheet Frontier Comparison
C2: Solver | H2: Shrunken Solver
C3: Risk | D3: Return | E3: Min(risk) | F3: Min(return) | H3: Risk | I3: Return | J3: Min(risk) | K3: Min(return)
C4: 0.1048344 | D4: 0.049474959 | E4: 0.1048344 | F4: 0.049474959 | H4: 0.13103874 | I4: 0.049467856 | J4: 0.13103874 | K4: 0.049467856
C5: 0.11997431 | D5: 0.055 | H5: 0.14270322 | I5: 0.055
C6: 0.13509377 | D6: 0.06 | H6: 0.15947944 | I6: 0.06
C7: 0.1496807 | D7: 0.065 | H7: 0.1725572 | I7: 0.065
C8: 0.16610478 | D8: 0.07 | H8: 0.18792806 | I8: 0.07
C9: 0.18261296 | D9: 0.075 | H9: 0.20555046 | I9: 0.075
C10: 0.20059708 | D10: 0.08 | H10: 0.2300199 | I10: 0.08
C11: 0.2217962 | D11: 0.085 | H11: 0.27687775 | I11: 0.085
C12: 0.25756701 | D12: 0.093207564 | E12: Max | H12: 0.30241049 | I12: 0.093207564 | J12: Max

Sheet Specific Portfolio 
A1: Ticker | B1: VTI | C1: VO | D1: VB | E1: VWUSX | F1: VLUE | G1: VYM | H1: VCR | I1: VHT | J1: SCHF | K1: VWO | L1: EFG | M1: IVLU | N1: VYMI | O1: FBNDX | P1: VWEHX | Q1: PICB | R1: HYXU | S1: Oil Basket | T1: Timber Basket | U1: STOR | W1: GSPC
A2: Returns | B2: 0.020135642 | C2: 0.023392872 | D2: 0.021898284 | E2: 0.02666322 | F2: -0.0059279467 | G2: 0.035551053 | H2: 0.023273062 | I2: 0.065273197 | J2: 0.0052099208 | K2: 0.048335784 | L2: 0.0074349554 | M2: -0.0033727917 | N2: 0.0088539492 | O2: 0.0052842108 | P2: -0.0070507259 | Q2: -0.012940664 | R2: -0.017561315 | S2: 0.010113431 | T2: -0.017080732 | U2: 0.032035467 | W2: 0.017859382
B3: -0.091761055 | C3: -0.098025633 | D3: -0.11112112 | E3: -0.09085557 | F3: -0.11052319 | G3: -0.086647546 | H3: -0.088754558 | I3: -0.091387839 | J3: -0.054022923 | K3: -0.033449906 | L3: -0.050489939 | M3: -0.062857088 | N3: -0.041566704 | O3: 0.015302994 | P3: -0.021294341 | Q3: 0.013770781 | R3: 0.0092931443 | S3: -0.095157768 | T3: -0.082211878 | U3: -0.044112867 | W3: -0.091776956
B4: 0.085402381 | C4: 0.10471827 | D4: 0.11712965 | E4: 0.094755476 | F4: 0.098387498 | G4: 0.061033574 | H4: 0.10085122 | I4: 0.059340365 | J4: 0.07195753 | K4: 0.096587827 | L4: 0.061676722 | M4: 0.080475472 | N4: 0.070375171 | O4: 0.015530912 | P4: 0.049409077 | Q4: 0.02918282 | R4: 0.023395434 | S4: 0.071385125 | T4: 0.14658667 | U4: 0.14164603 | W4: 0.078684405
B5: 0.035587945 | C5: 0.042581103 | D5: 0.048559231 | E5: 0.044093868 | F5: 0.01894367 | G5: 0.037703857 | H5: 0.015026781 | I5: 0.016398978 | J5: 0.024021045 | K5: -0.0038296917 | L5: 0.033410483 | M5: 0.0059243427 | N5: 0.015606851 | O5: 0.0010351346 | P5: 0.01501068 | Q5: 0.006008248 | R5: 0.012340873 | S5: 0.05027969 | T5: -0.041103701 | U5: 0.0046414171 | W5: 0.02972893
B6: 0.014167673 | C6: 0.013529287 | D6: -0.0085803286 | E6: 0.016683683 | F6: -0.0095208703 | G6: 0.0052353703 | H6: 0.027674923 | I6: 0.0038264212 | J6: 0.0061055866 | K6: 0.023148306 | L6: 0.022037338 | M6: -0.00075698964 | N6: 0.0021617997 | O6: 0.019336132 | P6: 0.0099693849 | Q6: 0.0078449642 | R6: -0.0039967891 | S6: 0.012047566 | T6: 0.0016050625 | U6: 0.041976313 | W6: 0.017924288
B7: 0.03925079 | C7: 0.037137855 | D7: 0.035863903 | E7: 0.14328428 | F7: 0.034184583 | G7: 0.028367844 | H7: 0.051041047 | I7: -0.026959034 | J7: 0.028744583 | K7: 0.021411964 | L7: 0.034990614 | M7: 0.01717745 | N7: 0.02842596 | O7: 0.0024170414 | P7: 0.014951046 | Q7: -0.00022520302 | R7: 0.012038483 | S7: -0.028668156 | T7: 0.039923455 | U7: -0.0053730284 | W7: 0.039313435
B8: -0.064498857 | C8: -0.060580456 | D8: -0.071771422 | E8: -0.060694927 | F8: -0.096016368 | G8: -0.063117328 | H8: -0.078969371 | I8: -0.026753652 | J8: -0.052157622 | K8: -0.063810271 | L8: -0.042040943 | M8: -0.073675848 | N8: -0.053363198 | O8: 0.015097145 | P8: -0.010827392 | Q8: -0.010945912 | R8: -0.019230848 | S8: -0.070668176 | T8: -0.1596295 | U8: 0.027010607 | W8: -0.065777726
B9: 0.070780583 | C9: 0.071010117 | D9: 0.069689174 | E9: 0.073475491 | F9: 0.095697945 | G9: 0.066443621 | H9: 0.077568828 | I9: 0.071989839 | J9: 0.059591161 | K9: 0.053718492 | L9: 0.064857947 | M9: 0.052624997 | N9: 0.053720491 | O9: 0.014776506 | P9: 0.027245509 | Q9: 0.033051183 | R9: 0.039417804 | S9: 0.070140348 | T9: 0.1520627 | U9: -0.020317144 | W9: 0.068930183
B10: 0.01412512 | C10: 0.013101356 | D10: 0.012000213 | E10: 0.012621592 | F10: 0.016011972 | G10: 0.0072099112 | H10: 0.011595048 | I10: -0.01305031 | J10: -0.019632322 | K10: -0.018104649 | L10: -0.011390358 | M10: -0.020824068 | N10: -0.02688181 | O10: 0.0023571247 | P10: 0.0044564918 | Q10: -0.013418341 | R10: -0.019642119 | S10: -0.022288071 | T10: -0.072549338 | U10: 0.030732144 | W10: 0.013128195
B11: -0.02082677 | C11: -0.027576177 | D11: -0.039674585 | E11: -0.01677858 | F11: -0.045217683 | G11: -0.021020431 | H11: -0.017358461 | I11: -0.011767143 | J11: -0.018753707 | K11: -0.03256711 | L11: -0.0055103326 | M11: -0.035445042 | N11: -0.034488336 | O11: 0.023245905 | P11: 0.0095835561 | Q11: 0.0088005908 | R11: 0.00039678611 | S11: -0.07278911 | T11: 0.045102442 | U11: 0.10377091 | W11: -0.018091653
B12: 0.017792804 | C12: 0.020970813 | D12: 0.013667671 | E12: -0.012189369 | F12: 0.048549396 | G12: 0.038954588 | H12: 0.013397385 | I12: -0.0079013048 | J12: 0.032069733 | K12: 0.0091090802 | L12: 0.013852226 | M12: 0.046853177 | N12: 0.041206644 | O12: -0.0038665768 | P12: 0.0042625336 | Q12: -0.0079514433 | R12: -0.0093199609 | S12: 0.043523102 | T12: 0.062331578 | U12: -6.1660721e-05 | W12: 0.017181168
B13: 0.021060071 | C13: 0.011098215 | D13: 0.016504843 | E13: 0.025419733 | F13: 0.028400774 | G13: 0.010481276 | H13: 0.0071065245 | I13: 0.047829499 | J13: 0.031387585 | K13: 0.039493334 | L13: 0.032666691 | M13: 0.039052051 | N13: 0.033002221 | O13: 0.0045210737 | P13: 0.0061315844 | Q13: 0.025883421 | R13: 0.023418804 | S13: -0.029235912 | T13: 0.10053296 | U13: 0.082598301 | W13: 0.020431747
B14: 0.037877539 | C14: 0.032219718 | D14: 0.041999844 | E14: 0.05126351 | F14: 0.03697992 | G14: 0.023421918 | H14: 0.018632982 | I14: 0.061297777 | J14: 0.012477044 | K14: 0.0050178266 | L14: 0.018041809 | M14: 0.013175886 | N14: 0.0073350213 | O14: -0.00036003731 | P14: 0.0059503643 | Q14: -0.0077801686 | R14: -0.00097779586 | S14: 0.041592632 | T14: 0.031100432 | U14: 0.005184972 | W14: 0.034047064
... B37: 0.066873818 | C37: 0.065889508 | D37: 0.049480953 | E37: 0.072737368 | F37: 0.024826216 | G37: 0.049250121 | H37: 0.093041262 | I37: 0.045678912 | J37: 0.03255814 | K37: 0.012997401 | L37: 0.042077581 | M37: 0.012057565 | N37: 0.029674489 | O37: -0.0011904762 | P37: -0.0066889632 | Q37: 0.0060383631 | R37: -0.0050881337 | S37: 0.11011797 | T37: 0.079032944 | U37: 0.07180768 | W37: 0.069143873
A38: Beta | B38: =SLOPE(B2:B37,W2:W37) -> 1.0290576 | C38: =SLOPE(C$2:C$37,$W$2:$W$37) -> 1.1063456 | D38: =SLOPE(D$2:D$37,$W$2:$W$37) -> 1.1927321 | E38: =SLOPE(E$2:E$37,$W$2:$W$37) -> 1.1027866 | F38: =SLOPE(F$2:F$37,$W$2:$W$37) -> 1.1038458 | G38: =SLOPE(G$2:G$37,$W$2:$W$37) -> 0.91877651 | H38: =SLOPE(H$2:H$37,$W$2:$W$37) -> 1.2682613 | I38: =SLOPE(I$2:I$37,$W$2:$W$37) -> 0.73932412 | J38: =SLOPE(J$2:J$37,$W$2:$W$37) -> 0.84071189 | ... U38: =SLOPE(U$2:U$37,$W$2:$W$37) -> 1.4737245
A39: Expected return | B39: =0.02+B38*(0.075-0.02) -> 0.07659817 | C39: =0.02+C38*(0.075-0.02) -> 0.08084901 | D39: =0.02+D38*(0.075-0.02) -> 0.085600267 | E39: =0.02+E38*(0.075-0.02) -> 0.080653261 | F39: =0.02+F38*(0.075-0.02) -> 0.08071152 | G39: =0.02+G38*(0.075-0.02) -> 0.070532708 | H39: =0.02+H38*(0.075-0.02) -> 0.089754373 | I39: =0.02+I38*(0.075-0.02) -> 0.060662826 | ... U39: =0.02+U38*(0.075-0.02) -> 0.10105485
B41: Fund | C41: VTI | D41: VO | E41: VB | F41: VWUSX | G41: VLUE | H41: VYM | I41: VCR | J41: VHT | K41: SCHF | L41: VWO | M41: EFG | N41: IVLU | O41: VYMI | P41: FBNDX | Q41: VWEHX | R41: PICB | S41: HYXU | T41: Oil Basket | U41: Timber Basket | V41: STOR
B42: Weights | C42: 0 | D42: 0 | E42: 0 | F42: 0 | G42: 0 | H42: 0 | I42: 0 | J42: 0.3 | K42: 0 | L42: 0 | M42: 0.4 | N42: 0 | O42: 0 | P42: 0.3 | Q42: 0 | R42: 0 | S42: 0 | T42: 0 | U42: 0 | V42: 0
B43: Working | C43: {=MMULT($C$42:$V$42,'Covariance Matrix'!B77:B96)} -> 0.028533253 | D43: {=MMULT($C$42:$V$42,'Covariance Matrix'!C77:C96)} -> 0.031645642 | E43: {=MMULT($C$42:$V$42,'Covariance Matrix'!D77:D96)} -> 0.035363869 | F43: {=MMULT($C$42:$V$42,'Covariance Matrix'!E77:E96)} -> 0.033757504 | G43: {=MMULT($C$42:$V$42,'Covariance Matrix'!F77:F96)} -> 0.033380134 | H43: {=MMULT($C$42:$V$42,'Covariance Matrix'!G77:G96)} -> 0.026685681 | I43: {=MMULT($C$42:$V$42,'Covariance Matrix'!H77:H96)} -> 0.036693329 | J43: {=MMULT($C$42:$V$42,'Covariance Matrix'!I77:I96)} -> 0.023249737 | ... V43: {=MMULT($C$42:$V$42,'Covariance Matrix'!U77:U96)} -> 0.05865464
B44: Class Weight | C44: =SUM(C42:J42) -> 0.3 | K44: =SUM(K42:O42) -> 0.4 | P44: =SUM(P42:S42) -> 0.3 | T44: =SUM(T42:V42) -> 0
B47: Sum Weight | C47: =SUM(C42:V42) -> 1 | H47: g = | I47: -14.2333 | K47: My Optimal Portfolio: | L47: Conservative | R47: VTI | S47: =C42 -> 0
B48: Risk(variance) | C48: {=MMULT(C43:V43,S47:S66)} -> 0.017171153 | D48: Risk (St.dev) | E48: =SQRT(C48) -> 0.13103874 | H48: l = | I48: 7.6167 | K48: Fund | L48: VHT | M48: EFG | N48: FBNDX | R48: VO | S48: =D42 -> 0
K49: Weight | L49: 0.3 | M49: 0.4 | N49: 0.3 | R49: VB | S49: =E42 -> 0
B50: Return | G50: Maximize | H50: mp – lsP2 | I50: =C51-I48*C48 -> -0.081319662 | R50: VWUSX | S50: =F42 -> 0
B51: Actual | C51: =SUMPRODUCT(C42:V42,B39:U39) -> 0.049467856 | R51: VLUE | S51: =G42 -> 0
B52: Desired (Target) | C52: 0 | R52: VYM | S52: =H42 -> 0
R53: VCR | S53: =I42 -> 0
B54: Class Constraints | C54: MIN | D54: Weights | E54: MAX | R54: VHT | S54: =J42 -> 0.3
B55: Class A | C55: 0.3 | D55: to | E55: 0.95 | R55: SCHF | S55: =K42 -> 0
B56: Class B | C56: 0.1 | D56: to | E56: 0.4 | R56: VWO | S56: =L42 -> 0
B57: Class C | C57: 0 | D57: to | E57: 0.7 | R57: EFG | S57: =M42 -> 0.4
B58: Class D | C58: 0 | D58: to | E58: 0.2 | R58: IVLU | S58: =N42 -> 0
N59: ` | R59: VYMI | S59: =O42 -> 0
R60: FBNDX | S60: =P42 -> 0.3
R61: VWEHX | S61: =Q42 -> 0
R62: PICB | S62: =R42 -> 0
R63: HYXU | S63: =S42 -> 0
R64: Oil Basket | S64: =T42 -> 0
R65: Timber Basket | S65: =U42 -> 0
R66: STOR | S66: =V42 -> 0
